{
  "215369658": {
    "Company": "Skyrocket Ventures",
    "Job Title": "Jr. to Lead Backend Engineer – Hypergrowth Fintech/Payments Startup",
    "Job Details": "DescriptionSkyrocket Ventures is a recruiting firm for hundreds of high growth technology companies that range from industry leaders to top-tier startups||||  This opportunity is with one of our client companies for a full-time permanent hire||||  Please only apply if you are authorized to work in the U||||S||||Please note that even if this job is not a perfect match, we encourage you to apply as long as it is in the ballpark||||  Companies are often flexible in hiring candidates who do not perfectly fit their written job description, as long as the most important qualifications are there and the candidate is good in general||||Most of the jobs we are recruiting for are not posted online, so if you would like to know of all the opportunities we have that match your interests and qualifications, then please get in touch with us||||Thank you!Matthew StrassbergRecruiting DirectorSkyrocket VenturesFeel free to check out testimonials from some of our many candidates/clients here:http://www||||linkedin||||com/in/mstrassbergJr|||| to Lead Backend Engineer – Hypergrowth Fintech/Payments StartupLocation:  You can either work in San Francisco or Santa Clara (whichever you prefer) This company’s product is a B2B payments platform||||  The company is in hypergrowth; revenues have multiplied year over year, and the company grew from about 20 employees in June 2019 to over 50 a few months later||||  The company has many openings, including multiple openings for backend engineers (from jr|||| to lead level), and has 2 offices in the Bay Area so that it can hire rapidly||||The company will offer salary up to $200k as well as equity which could be lucrative||||Job Responsibilities:- Working on the core business logic, including onboarding and verification, money movement, notifications, reporting, risk and fraud, and analytic tools- Working with REST APIs- Using encryption and best practices to make sure that data and communications are secure- Collaborating closely with DBAs to design high performance queries and scalable- Contributing to the architecture of core systems to scale in a distributed fashion||||  Incorporating database sharding, caching, concurrent & parallel computing, messaging, etc|||| to achieve 24x7 reliability- (if Lead level) Helping to mentor junior engineers- Closely collaborating with cross-functional teams in Product, Marketing, and OperationsQualifications:- Either 1) experienced in Java, or 2) willing to learn and primarily use Java, and experienced in at least one of:  Scala, Go, Python, or C++- A Bachelor’s degree in Computer Science or equivalent experience||||  Strong Computer Science fundamentals, including algorithms, data structures, design patterns, etc||||- Experience with RDBMS such as MySQL and PostgreSQL- Open, direct, and honest communication- Ability to thrive in a fast-paced, highly collaborative environment - Commitment to coding best practices including code reviews and unit testing- Passion for learning and constant improvementNice to Haves:- Experience in an early to mid stage startup- Experience working in fintech and/or payments- Experience with either AWS or another cloud platform such as Rackspace or Azure or Google Cloud- Experience with NoSQL, Redis, Cassandra- Experience with Kafka, Kinesis- Experience building highly available, large scale distributed systemsDid you like this job or want to see more?  All of our online job postings can be found on these sites:https://www||||dice||||com/company/10366547https://www||||monster||||com/jobs/c-skyrocket-ventures||||aspxhttps://www||||linkedin||||com/jobs/skyrocket-ventures-jobsFollow us on Instagram here:https://www||||instagram||||com/skyrocketventuresFollow us on LinkedIn here:https://www||||linkedin||||com/company/skyrocket-venturesJob DetailsSalary$120000 - $200000 Per YearJob Typefulltime, employeePosted 10 days ago||||",
    "KeyWords": {
      "NOUN": {
        "Ventures": "Ventures",
        "recruiting": "recruiting",
        "firm": "firm",
        "hundreds": "hundreds",
        "growth": "growth",
        "technology": "technology",
        "companies": "companies",
        "industry": "industry",
        "leaders": "leaders",
        "startups": "startups",
        "opportunity": "opportunity",
        "client": "client",
        "hire": "hire",
        "Please": "Please",
        "U.": "U.",
        "S.": "S.",
        "job": "job",
        "match": "match",
        "ballpark": "ballpark",
        "Companies": "Companies",
        "candidates": "candidates",
        "description": "description",
        "qualifications": "qualifications",
        "candidate": "candidate",
        "jobs": "jobs",
        "online": "online",
        "opportunities": "opportunities",
        "interests": "interests",
        "touch": "touch",
        "Matthew": "Matthew",
        "DirectorSkyrocket": "DirectorSkyrocket",
        "VenturesFeel": "VenturesFeel",
        "testimonials": "testimonials",
        "candidates/clients": "candidates/clients",
        "http": "http",
        "//www": "//www",
        "linkedin": "linkedin",
        "com/in/mstrassbergJr": "com/in/mstrassbergJr",
        "Backend": "Backend",
        "Engineer": "Engineer",
        "Hypergrowth": "Hypergrowth",
        "Fintech/Payments": "Fintech/Payments",
        "StartupLocation": "StartupLocation",
        "work": "work",
        "San": "San",
        "Francisco": "Francisco",
        "Santa": "Santa",
        "Clara": "Clara",
        "company": "company",
        "product": "product",
        "payments": "payments",
        "platform": "platform",
        "hypergrowth": "hypergrowth",
        "revenues": "revenues",
        "year": "year",
        "employees": "employees",
        "June": "June",
        "months": "months",
        "openings": "openings",
        "backend": "backend",
        "engineers": "engineers",
        "jr.": "jr.",
        "level": "level",
        "offices": "offices",
        "Bay": "Bay",
        "Area": "Area",
        "equity": "equity",
        "Responsibilities": "Responsibilities",
        "core": "core",
        "business": "business",
        "logic": "logic",
        "verification": "verification",
        "money": "money",
        "movement": "movement",
        "notifications": "notifications",
        "reporting": "reporting",
        "risk": "risk",
        "fraud": "fraud",
        "REST": "REST",
        "APIs-": "APIs-",
        "Using": "Using",
        "encryption": "encryption",
        "practices": "practices",
        "data": "data",
        "communications": "communications",
        "Collaborating": "Collaborating",
        "DBAs": "DBAs",
        "performance": "performance",
        "queries": "queries",
        "Contributing": "Contributing",
        "architecture": "architecture",
        "systems": "systems",
        "fashion": "fashion",
        "database": "database",
        "sharding": "sharding",
        "concurrent": "concurrent",
        "parallel": "parallel",
        "computing": "computing",
        "messaging": "messaging",
        "reliability-": "reliability-",
        "Lead": "Lead",
        "Closely": "Closely",
        "teams": "teams",
        "Product": "Product",
        "Marketing": "Marketing",
        "OperationsQualifications": "OperationsQualifications",
        "Java": "Java",
        "Scala": "Scala",
        "Go": "Go",
        "Python": "Python",
        "Bachelor": "Bachelor",
        "degree": "degree",
        "Computer": "Computer",
        "Science": "Science",
        "experience": "experience",
        "fundamentals": "fundamentals",
        "algorithms": "algorithms",
        "structures": "structures",
        "design": "design",
        "patterns": "patterns",
        "Experience": "Experience",
        "RDBMS": "RDBMS",
        "MySQL": "MySQL",
        "PostgreSQL-": "PostgreSQL-",
        "Open": "Open",
        "Ability": "Ability",
        "environment": "environment",
        "Commitment": "Commitment",
        "code": "code",
        "reviews": "reviews",
        "unit": "unit",
        "Passion": "Passion",
        "improvementNice": "improvementNice",
        "Haves": "Haves",
        "AWS": "AWS",
        "Rackspace": "Rackspace",
        "Azure": "Azure",
        "Google": "Google",
        "Cloud-": "Cloud-",
        "NoSQL": "NoSQL",
        "Redis": "Redis",
        "Cassandra-": "Cassandra-",
        "Kafka": "Kafka",
        "Kinesis-": "Kinesis-",
        "building": "building",
        "scale": "scale",
        "postings": "postings",
        "sites": "sites",
        "https": "https",
        "dice": "dice",
        "com/company/10366547https": "com/company/10366547https",
        "monster": "monster",
        "com/jobs/c-skyrocket-ventures": "com/jobs/c-skyrocket-ventures",
        "aspxhttps": "aspxhttps",
        "Instagram": "Instagram",
        "instagram": "instagram",
        "LinkedIn": "LinkedIn",
        "DetailsSalary": "DetailsSalary",
        "Per": "Per",
        "YearJob": "YearJob",
        "Typefulltime": "Typefulltime",
        "days": "days"
      },
      "VERB": {
        "range": "range",
        "is": "is",
        "apply": "apply",
        "are": "are",
        "authorized": "authorized",
        "work": "work",
        "note": "note",
        "encourage": "encourage",
        "hiring": "hiring",
        "do": "do",
        "fit": "fit",
        "written": "written",
        "recruiting": "recruiting",
        "posted": "posted",
        "would": "would",
        "like": "like",
        "know": "know",
        "have": "have",
        "match": "match",
        "please": "please",
        "get": "get",
        "Thank": "Thank",
        "StrassbergRecruiting": "StrassbergRecruiting",
        "check": "check",
        "Lead": "Lead",
        "can": "can",
        "either": "either",
        "prefer": "prefer",
        "multiplied": "multiplied",
        "grew": "grew",
        "has": "has",
        "including": "including",
        "lead": "lead",
        "hire": "hire",
        "will": "will",
        "offer": "offer",
        "could": "could",
        "be": "be",
        "Working": "Working",
        "onboarding": "onboarding",
        "make": "make",
        "design": "design",
        "scale": "scale",
        "Incorporating": "Incorporating",
        "caching": "caching",
        "achieve": "achieve",
        "Helping": "Helping",
        "mentor": "mentor",
        "collaborating": "collaborating",
        "experienced": "experienced",
        "learn": "learn",
        "use": "use",
        "C++-": "C++-",
        "thrive": "thrive",
        "coding": "coding",
        "learning": "learning",
        "mid": "mid",
        "working": "working",
        "distributed": "distributed",
        "want": "want",
        "see": "see",
        "found": "found",
        "com/skyrocketventuresFollow": "com/skyrocketventuresFollow",
        "employeePosted": "employeePosted"
      },
      "ADJ": {
        "top-tier": "top-tier",
        "full-time": "full-time",
        "permanent": "permanent",
        "perfect": "perfect",
        "flexible": "flexible",
        "important": "important",
        "good": "good",
        "general": "general",
        "Most": "Most",
        "free": "free",
        "many": "many",
        "B2B": "B2B",
        "few": "few",
        "multiple": "multiple",
        "salary": "salary",
        "lucrative": "lucrative",
        "Job": "Job",
        "analytic": "analytic",
        "tools-": "tools-",
        "best": "best",
        "sure": "sure",
        "secure-": "secure-",
        "high": "high",
        "scalable-": "scalable-",
        "distributed": "distributed",
        "junior": "junior",
        "engineers-": "engineers-",
        "cross-functional": "cross-functional",
        "willing": "willing",
        "least": "least",
        "equivalent": "equivalent",
        "Strong": "Strong",
        "such": "such",
        "direct": "direct",
        "honest": "honest",
        "communication-": "communication-",
        "fast-paced": "fast-paced",
        "collaborative": "collaborative",
        "testing-": "testing-",
        "constant": "constant",
        "early": "early",
        "stage": "stage",
        "startup-": "startup-",
        "fintech": "fintech",
        "and/or": "and/or",
        "payments-": "payments-",
        "cloud": "cloud",
        "available": "available",
        "large": "large",
        "more": "more",
        "online": "online",
        "com/jobs/skyrocket-ventures-jobsFollow": "com/jobs/skyrocket-ventures-jobsFollow",
        "com/company/skyrocket-venturesJob": "com/company/skyrocket-venturesJob"
      },
      "PRT": {
        "to": "to",
        "out": "out"
      },
      "NUM": {
        "10": "10",
        "20": "20",
        "50": "50",
        "2019": "2019",
        "120000": "120000",
        "200000": "200000",
        "200k": "200k",
        "24x7": "24x7",
        "one": "one"
      },
      "X": {
        "etc": "etc"
      }
    }
  },
  "217061850": {
    "Company": "Flexton Inc",
    "Job Title": "Jr Data Scientist",
    "Job Details": "DescriptionHi,Greetings,We have new requirement for Jr Data Scientist with our direct client at Mountain view, CA||||Please find the JD belowResponsibilities:● Extract and analyze LinkedIn Real Estate, Commissions, Credit Services, and other Finance data to derive actionable insights● Build the foundation for an emerging Data Science organization within the LinkedIn Finance Org● Design and analyze experiments to test new insight ideas and convert the results into actionable business recommendations● As an end consumer of the data, determine the tracking necessary to enable analytics of our financial & real estate data and features by working closely with infrastructure partners and data partners● Enable others in the organization to utilize your work by creating reusable artifacts● Develop models and data-driven solutions that add material lift to principal performance metricsBasic Qualifications:● BS/MS degree in a quantitative discipline: statistics, applied mathematics, operations research, computer science, engineering, economics, etc||||● 2+ years of experience developing applications, software and web analytics● 2+ years of work experience providing analytical insights and business reports to product or business functions● 2+ years of experience with Power BI, Tableau, QlikView, Microstrategy or other data visualization and BI dashboarding tools● 1+ years of experience programming in R and Python and working with large datasetsPreferred Qualifications:● PhD in a quantitative discipline: statistics, applied mathematics, operations research, computer science, engineering, economics, etc||||● Experience presenting insights to senior management on a regular basis● Expertise in applied statistics and in at least one statistical software package, preferably R & Python● Proficiency in SQL● Ability to communicate findings clearly to both technical and non-technical audiences● Ability to translate business objectives into actionable analysesExperience in working with large, diverse datasets from multiple data sourcesExperience in data cleansing, enrichment and data imputationJob DetailsJob Typefulltime, employeePosted 12 days ago||||",
    "KeyWords": {
      "NOUN": {
        "Greetings": "Greetings",
        "requirement": "requirement",
        "Jr": "Jr",
        "Data": "Data",
        "Scientist": "Scientist",
        "client": "client",
        "Mountain": "Mountain",
        "view": "view",
        "CA": "CA",
        "Please": "Please",
        "JD": "JD",
        "belowResponsibilities": "belowResponsibilities",
        "Extract": "Extract",
        "LinkedIn": "LinkedIn",
        "Real": "Real",
        "Estate": "Estate",
        "Commissions": "Commissions",
        "Credit": "Credit",
        "Services": "Services",
        "Finance": "Finance",
        "data": "data",
        "insights●": "insights●",
        "Build": "Build",
        "foundation": "foundation",
        "Science": "Science",
        "organization": "organization",
        "Org●": "Org●",
        "Design": "Design",
        "experiments": "experiments",
        "insight": "insight",
        "ideas": "ideas",
        "results": "results",
        "business": "business",
        "recommendations●": "recommendations●",
        "end": "end",
        "consumer": "consumer",
        "analytics": "analytics",
        "estate": "estate",
        "features": "features",
        "infrastructure": "infrastructure",
        "partners": "partners",
        "partners●": "partners●",
        "others": "others",
        "work": "work",
        "artifacts●": "artifacts●",
        "Develop": "Develop",
        "models": "models",
        "solutions": "solutions",
        "lift": "lift",
        "performance": "performance",
        "Qualifications": "Qualifications",
        "BS/MS": "BS/MS",
        "degree": "degree",
        "discipline": "discipline",
        "statistics": "statistics",
        "mathematics": "mathematics",
        "operations": "operations",
        "research": "research",
        "computer": "computer",
        "science": "science",
        "engineering": "engineering",
        "economics": "economics",
        "years": "years",
        "experience": "experience",
        "applications": "applications",
        "software": "software",
        "web": "web",
        "insights": "insights",
        "reports": "reports",
        "product": "product",
        "Power": "Power",
        "BI": "BI",
        "Tableau": "Tableau",
        "QlikView": "QlikView",
        "Microstrategy": "Microstrategy",
        "visualization": "visualization",
        "programming": "programming",
        "Python": "Python",
        "PhD": "PhD",
        "Experience": "Experience",
        "management": "management",
        "basis●": "basis●",
        "Expertise": "Expertise",
        "package": "package",
        "Python●": "Python●",
        "Proficiency": "Proficiency",
        "SQL●": "SQL●",
        "Ability": "Ability",
        "findings": "findings",
        "audiences●": "audiences●",
        "objectives": "objectives",
        "analysesExperience": "analysesExperience",
        "datasets": "datasets",
        "sourcesExperience": "sourcesExperience",
        "cleansing": "cleansing",
        "enrichment": "enrichment",
        "imputationJob": "imputationJob",
        "DetailsJob": "DetailsJob",
        "Typefulltime": "Typefulltime",
        "days": "days"
      },
      "VERB": {
        "find": "find",
        "derive": "derive",
        "emerging": "emerging",
        "test": "test",
        "convert": "convert",
        "determine": "determine",
        "tracking": "tracking",
        "enable": "enable",
        "working": "working",
        "utilize": "utilize",
        "creating": "creating",
        "add": "add",
        "applied": "applied",
        "developing": "developing",
        "analytics●": "analytics●",
        "providing": "providing",
        "dashboarding": "dashboarding",
        "presenting": "presenting",
        "communicate": "communicate",
        "translate": "translate",
        "employeePosted": "employeePosted"
      },
      "ADJ": {
        "direct": "direct",
        "other": "other",
        "actionable": "actionable",
        "analyze": "analyze",
        "new": "new",
        "necessary": "necessary",
        "financial": "financial",
        "real": "real",
        "Enable": "Enable",
        "reusable": "reusable",
        "data-driven": "data-driven",
        "material": "material",
        "principal": "principal",
        "metricsBasic": "metricsBasic",
        "quantitative": "quantitative",
        "analytical": "analytical",
        "large": "large",
        "datasetsPreferred": "datasetsPreferred",
        "senior": "senior",
        "regular": "regular",
        "applied": "applied",
        "least": "least",
        "statistical": "statistical",
        "technical": "technical",
        "non-technical": "non-technical",
        "diverse": "diverse",
        "multiple": "multiple"
      },
      "PRT": {
        "to": "to"
      },
      "X": {
        "etc": "etc"
      },
      "NUM": {
        "12": "12",
        "2+": "2+",
        "1+": "1+",
        "one": "one"
      }
    }
  },
  "217322582": {
    "Company": "E-TRADE",
    "Job Title": "DevOps Engineer",
    "Job Details": "DescriptionMore than 30 years ago, E*TRADE pioneered the online brokerage industry by executing the first-ever electronic individual investor trade|||| While the landscape of our industry has changed dramatically, our culture of innovation and drive to make online trading accessible to everyone continues to drive us forward|||| We believe in challenging the status quo, fostering an environment of curiosity and learning, and, above all, putting our customers first||||SummaryWe are looking for a DevOps team player with good interpersonal skills to join our team|||| You will have the opportunity to work on technologies such as Python/Django, Rest APIs, Celery distributed task queue, Ansible, Jenkins Pipeline, Elaticsearch, Grafana to name a few||||Responsibilities Design, build, and maintain efficient, reusable, and reliable Python codeIdentify bottlenecks and bugs, and provide solutionsHelp maintain code quality, organization and automatizationIdentify automation opportunities to improve DevOps operations REQUIREMENTSRequirements 2+ years of experience in a distributed online consumer applications environmentHave experience or at least strong interest in tools development and automationPassion for writing great, simple, clean, efficient codeExcited to learn new technologies and tools as our applications and systems evolveExperience in Scrum development techniques a plus Working in a team environment where attention to source management, quality and code documentation is expectedDegree in Computer Science or equivalent We offer a competitive and comprehensive benefits package|||| Please visit https://www||||etradecareers||||com/why-work-at-etrade/employee-benefits/ to learn more about the opportunities||||E*TRADE Financial is an Equal Opportunity Employer who encourages diversity in the workplace|||| All qualified applicants will receive consideration for employment without regard to race, color, national origin, religion, sex, age, disability, citizenship, marital status, sexual orientation, gender identity, military or protected veteran status, or any other characteristic protected by applicable law||||Job DetailsJob Typefulltime, employeePosted 12 days ago||||",
    "KeyWords": {
      "ADJ": {
        "online": "online",
        "first-ever": "first-ever",
        "electronic": "electronic",
        "individual": "individual",
        "accessible": "accessible",
        "good": "good",
        "interpersonal": "interpersonal",
        "such": "such",
        "few": "few",
        "efficient": "efficient",
        "reusable": "reusable",
        "reliable": "reliable",
        "distributed": "distributed",
        "least": "least",
        "strong": "strong",
        "great": "great",
        "simple": "simple",
        "clean": "clean",
        "new": "new",
        "plus": "plus",
        "expectedDegree": "expectedDegree",
        "competitive": "competitive",
        "comprehensive": "comprehensive",
        "more": "more",
        "Equal": "Equal",
        "qualified": "qualified",
        "national": "national",
        "marital": "marital",
        "sexual": "sexual",
        "military": "military",
        "other": "other",
        "characteristic": "characteristic",
        "applicable": "applicable"
      },
      "NUM": {
        "12": "12",
        "2+": "2+"
      },
      "NOUN": {
        "TRADE": "TRADE",
        "brokerage": "brokerage",
        "industry": "industry",
        "investor": "investor",
        "trade": "trade",
        "landscape": "landscape",
        "culture": "culture",
        "innovation": "innovation",
        "drive": "drive",
        "trading": "trading",
        "everyone": "everyone",
        "status": "status",
        "quo": "quo",
        "environment": "environment",
        "curiosity": "curiosity",
        "learning": "learning",
        "customers": "customers",
        "SummaryWe": "SummaryWe",
        "DevOps": "DevOps",
        "team": "team",
        "player": "player",
        "skills": "skills",
        "opportunity": "opportunity",
        "technologies": "technologies",
        "Python/Django": "Python/Django",
        "Rest": "Rest",
        "APIs": "APIs",
        "Celery": "Celery",
        "task": "task",
        "queue": "queue",
        "Ansible": "Ansible",
        "Jenkins": "Jenkins",
        "Pipeline": "Pipeline",
        "Elaticsearch": "Elaticsearch",
        "Grafana": "Grafana",
        "Responsibilities": "Responsibilities",
        "Design": "Design",
        "build": "build",
        "Python": "Python",
        "codeIdentify": "codeIdentify",
        "bottlenecks": "bottlenecks",
        "bugs": "bugs",
        "solutionsHelp": "solutionsHelp",
        "maintain": "maintain",
        "code": "code",
        "quality": "quality",
        "organization": "organization",
        "automation": "automation",
        "opportunities": "opportunities",
        "operations": "operations",
        "years": "years",
        "experience": "experience",
        "consumer": "consumer",
        "applications": "applications",
        "interest": "interest",
        "tools": "tools",
        "development": "development",
        "automationPassion": "automationPassion",
        "systems": "systems",
        "evolveExperience": "evolveExperience",
        "Scrum": "Scrum",
        "Working": "Working",
        "attention": "attention",
        "source": "source",
        "management": "management",
        "documentation": "documentation",
        "Computer": "Computer",
        "Science": "Science",
        "equivalent": "equivalent",
        "benefits": "benefits",
        "package": "package",
        "Please": "Please",
        "visit": "visit",
        "https": "https",
        "//www": "//www",
        "etradecareers": "etradecareers",
        "com/why-work-at-etrade/employee-benefits/": "com/why-work-at-etrade/employee-benefits/",
        "Financial": "Financial",
        "Opportunity": "Opportunity",
        "Employer": "Employer",
        "diversity": "diversity",
        "workplace": "workplace",
        "applicants": "applicants",
        "consideration": "consideration",
        "employment": "employment",
        "regard": "regard",
        "race": "race",
        "color": "color",
        "origin": "origin",
        "religion": "religion",
        "sex": "sex",
        "age": "age",
        "disability": "disability",
        "citizenship": "citizenship",
        "orientation": "orientation",
        "gender": "gender",
        "identity": "identity",
        "veteran": "veteran",
        "law": "law",
        "Job": "Job",
        "DetailsJob": "DetailsJob",
        "Typefulltime": "Typefulltime",
        "days": "days"
      },
      "VERB": {
        "executing": "executing",
        "has": "has",
        "changed": "changed",
        "make": "make",
        "continues": "continues",
        "drive": "drive",
        "believe": "believe",
        "challenging": "challenging",
        "fostering": "fostering",
        "putting": "putting",
        "are": "are",
        "looking": "looking",
        "join": "join",
        "will": "will",
        "have": "have",
        "work": "work",
        "distributed": "distributed",
        "name": "name",
        "maintain": "maintain",
        "provide": "provide",
        "automatizationIdentify": "automatizationIdentify",
        "improve": "improve",
        "REQUIREMENTSRequirements": "REQUIREMENTSRequirements",
        "environmentHave": "environmentHave",
        "writing": "writing",
        "codeExcited": "codeExcited",
        "learn": "learn",
        "techniques": "techniques",
        "is": "is",
        "offer": "offer",
        "encourages": "encourages",
        "receive": "receive",
        "protected": "protected",
        "employeePosted": "employeePosted"
      },
      "PRT": {
        "to": "to"
      }
    }
  },
  "217322586": {
    "Company": "E-TRADE",
    "Job Title": "Principal, Middleware Engineer",
    "Job Details": "DescriptionMore than 30 years ago, E*TRADE pioneered the online brokerage industry by executing the first-ever electronic individual investor trade|||| While the landscape of our industry has changed dramatically, our culture of innovation and drive to make online trading accessible to everyone continues to drive us forward|||| We believe in challenging the status quo, fostering an environment of curiosity and learning, and, above all, putting our customers first||||SummaryWe are looking for a Senior middleware engineer to work on cutting edge technologies in a multi-platform environment|||| You will be responsible for designing, configuring, installing, and administering JBoss/Tomcat servers||||ResponsibilitiesDevelop messaging system design specifications for new applications that require real-time messaging featureBe the subject matter expert on messaging systems|||| Collaborate with end users and provide guidance and best practices||||Troubleshoot and resolve issues related to messaging systemsPerform research and adapt and/or create tools to help monitor and manage our messaging systems Perform configuration and deployment tasks to roll changes to all environmentsPerform basic tests, performance tests, and fail over tests on an on-going basisDevelop and maintain documents for system architecture and operationsPerform regular upgrades to keep our messaging systems up-to-date REQUIREMENTSRequirements7+ years of experience in a distributed online consumer applications environmentExperience with messaging systems, preferability ActiveMQ||||Experience with Java programming languageExperience with highly scalable and distributed infrastructureExposure to web-based software development or operationsStrong experience with scripting languages and using them in automation (primarily Bash and Python)|||| Experience working with containers and container-orchestration tools like Docker and Kubernetes is a plusPassion for best practices in computer science disciplines, object orientation, test driven design, and code reuseExcited to learn new technologies and tools as our applications and systems changesExperience in Scrum development techniques a plus as is working in a team environment where attention to source management, quality and code documentation is expectedStrong communication skills are required as this position require interaction across many different teams|||| Degree in Computer Science or equivalent We offer a competitive and comprehensive benefits package|||| Please visit https://www||||etradecareers||||com/why-work-at-etrade/employee-benefits/ to learn more about the opportunities||||E*TRADE Financial is an Equal Opportunity Employer who encourages diversity in the workplace|||| All qualified applicants will receive consideration for employment without regard to race, color, national origin, religion, sex, age, disability, citizenship, marital status, sexual orientation, gender identity, military or protected veteran status, or any other characteristic protected by applicable law||||Job DetailsJob Typefulltime, employeePosted 12 days ago||||",
    "KeyWords": {
      "ADJ": {
        "online": "online",
        "first-ever": "first-ever",
        "electronic": "electronic",
        "individual": "individual",
        "accessible": "accessible",
        "multi-platform": "multi-platform",
        "responsible": "responsible",
        "new": "new",
        "real-time": "real-time",
        "subject": "subject",
        "best": "best",
        "systemsPerform": "systemsPerform",
        "adapt": "adapt",
        "environmentsPerform": "environmentsPerform",
        "basic": "basic",
        "on-going": "on-going",
        "regular": "regular",
        "up-to-date": "up-to-date",
        "distributed": "distributed",
        "scalable": "scalable",
        "web-based": "web-based",
        "operationsStrong": "operationsStrong",
        "object": "object",
        "expectedStrong": "expectedStrong",
        "many": "many",
        "different": "different",
        "competitive": "competitive",
        "comprehensive": "comprehensive",
        "more": "more",
        "Equal": "Equal",
        "qualified": "qualified",
        "national": "national",
        "marital": "marital",
        "sexual": "sexual",
        "military": "military",
        "other": "other",
        "characteristic": "characteristic",
        "applicable": "applicable"
      },
      "NUM": {
        "12": "12"
      },
      "NOUN": {
        "TRADE": "TRADE",
        "brokerage": "brokerage",
        "industry": "industry",
        "investor": "investor",
        "trade": "trade",
        "landscape": "landscape",
        "culture": "culture",
        "innovation": "innovation",
        "drive": "drive",
        "trading": "trading",
        "everyone": "everyone",
        "status": "status",
        "quo": "quo",
        "environment": "environment",
        "curiosity": "curiosity",
        "learning": "learning",
        "customers": "customers",
        "SummaryWe": "SummaryWe",
        "Senior": "Senior",
        "middleware": "middleware",
        "engineer": "engineer",
        "edge": "edge",
        "technologies": "technologies",
        "installing": "installing",
        "JBoss/Tomcat": "JBoss/Tomcat",
        "servers": "servers",
        "ResponsibilitiesDevelop": "ResponsibilitiesDevelop",
        "system": "system",
        "design": "design",
        "specifications": "specifications",
        "applications": "applications",
        "messaging": "messaging",
        "matter": "matter",
        "expert": "expert",
        "systems": "systems",
        "Collaborate": "Collaborate",
        "end": "end",
        "users": "users",
        "guidance": "guidance",
        "practices": "practices",
        "Troubleshoot": "Troubleshoot",
        "issues": "issues",
        "research": "research",
        "and/or": "and/or",
        "create": "create",
        "tools": "tools",
        "monitor": "monitor",
        "Perform": "Perform",
        "configuration": "configuration",
        "deployment": "deployment",
        "tasks": "tasks",
        "changes": "changes",
        "tests": "tests",
        "performance": "performance",
        "basisDevelop": "basisDevelop",
        "maintain": "maintain",
        "documents": "documents",
        "architecture": "architecture",
        "upgrades": "upgrades",
        "REQUIREMENTSRequirements7+": "REQUIREMENTSRequirements7+",
        "years": "years",
        "experience": "experience",
        "consumer": "consumer",
        "environmentExperience": "environmentExperience",
        "preferability": "preferability",
        "ActiveMQ": "ActiveMQ",
        "Experience": "Experience",
        "Java": "Java",
        "languageExperience": "languageExperience",
        "infrastructureExposure": "infrastructureExposure",
        "software": "software",
        "development": "development",
        "scripting": "scripting",
        "languages": "languages",
        "automation": "automation",
        "Bash": "Bash",
        "Python": "Python",
        "containers": "containers",
        "container-orchestration": "container-orchestration",
        "Docker": "Docker",
        "Kubernetes": "Kubernetes",
        "plusPassion": "plusPassion",
        "computer": "computer",
        "science": "science",
        "disciplines": "disciplines",
        "orientation": "orientation",
        "test": "test",
        "driven": "driven",
        "code": "code",
        "changesExperience": "changesExperience",
        "Scrum": "Scrum",
        "plus": "plus",
        "team": "team",
        "attention": "attention",
        "source": "source",
        "management": "management",
        "quality": "quality",
        "documentation": "documentation",
        "communication": "communication",
        "skills": "skills",
        "position": "position",
        "interaction": "interaction",
        "teams": "teams",
        "Degree": "Degree",
        "Computer": "Computer",
        "Science": "Science",
        "equivalent": "equivalent",
        "benefits": "benefits",
        "package": "package",
        "Please": "Please",
        "visit": "visit",
        "https": "https",
        "//www": "//www",
        "etradecareers": "etradecareers",
        "com/why-work-at-etrade/employee-benefits/": "com/why-work-at-etrade/employee-benefits/",
        "opportunities": "opportunities",
        "Financial": "Financial",
        "Opportunity": "Opportunity",
        "Employer": "Employer",
        "diversity": "diversity",
        "workplace": "workplace",
        "applicants": "applicants",
        "consideration": "consideration",
        "employment": "employment",
        "regard": "regard",
        "race": "race",
        "color": "color",
        "origin": "origin",
        "religion": "religion",
        "sex": "sex",
        "age": "age",
        "disability": "disability",
        "citizenship": "citizenship",
        "gender": "gender",
        "identity": "identity",
        "veteran": "veteran",
        "law": "law",
        "Job": "Job",
        "DetailsJob": "DetailsJob",
        "Typefulltime": "Typefulltime",
        "days": "days"
      },
      "VERB": {
        "executing": "executing",
        "has": "has",
        "changed": "changed",
        "make": "make",
        "continues": "continues",
        "drive": "drive",
        "believe": "believe",
        "challenging": "challenging",
        "fostering": "fostering",
        "putting": "putting",
        "are": "are",
        "looking": "looking",
        "work": "work",
        "cutting": "cutting",
        "will": "will",
        "be": "be",
        "designing": "designing",
        "configuring": "configuring",
        "administering": "administering",
        "messaging": "messaging",
        "require": "require",
        "featureBe": "featureBe",
        "provide": "provide",
        "resolve": "resolve",
        "related": "related",
        "help": "help",
        "manage": "manage",
        "roll": "roll",
        "fail": "fail",
        "operationsPerform": "operationsPerform",
        "keep": "keep",
        "programming": "programming",
        "using": "using",
        "working": "working",
        "is": "is",
        "reuseExcited": "reuseExcited",
        "learn": "learn",
        "techniques": "techniques",
        "required": "required",
        "offer": "offer",
        "encourages": "encourages",
        "receive": "receive",
        "protected": "protected",
        "employeePosted": "employeePosted"
      },
      "PRT": {
        "to": "to"
      }
    }
  },
  "217427379": {
    "Company": "GTT, LLC",
    "Job Title": "Data Scientist",
    "Job Details": "DescriptionData Scientist, Senior – IT Data & Analytics Team Overview At client, the Data and Analytics organization is focused on unlocking the value of client's data to support the company's Wildfire Safety Program||||  As part of that focus, we focus on delivering data and AI/Client centric products to support these initiatives||||  Some of the products that are being delivered include Remote Inspections, AI Enabled Inspections, Vegetation Management through LiDAR capabilities, Transmission Line Asset Data Foundation, Electric Distribution Asset Data Foundation, Asset Risk Modeling, and a Cloud Native Foundational Platform|||| A critical part of how we operate is to apply design thinking, work and observe the Agile development methodology, and co-location||||  Through these principles, we work as product teams to help deliver a valuable product to our business|||| Data Scientist Position Summary: We are seeking a Senior Data Scientist for the Data & Analytics Team||||  The successful candidate will join a product delivery team, following best-practice agile and data science techniques to deliver impactful data products for internal client partners||||  You will participate in the end-to-end lifecycle of model development, from initial user discovery through data engineering, feature engineering, model training and validation to model deployment as part of a business-facing product||||  You will actively participate and practice in an open, highly collaborative Agile environment, joining an existing, mature data science practice|||| Data Scientist Position Responsibilities: Applies machine learning and other analytical modeling methods to develop robust and reliable analytical models, including visualizations, within client's software development environment|||| Gathers, cleans, transforms, and/or reduces data from dissimilar sources from across client Collaborates with team members and stakeholders to effectively manage the lifecycle of a model, retraining, replacing or sunsetting models when appropriate|||| Shares and collaborates with other client data scientists|||| Delivers best-in-class software as part of a software delivery team|||| Minimum Education/Skills: Bachelor's Degree in Econometrics, Economics, Engineering, Mathematics, Applied Sciences, Statistics or job-related discipline or equivalent experience Job-related experience, 5 years, OR Master's Degree and job-related experience, 3 years, OR Doctorate Desired Education / Skills: Experience with the data science lifecycle, including data engineering, feature engineering, model building and evaluation, model deployment|||| Knowledge of commonly used data science programming languages, packages, and tools, especially Python|||| Understanding of data science/machine learning models and algorithms, not limited to: deep learning (CNN, RNN etc), decision trees (e||||g|||| xgboost, random forest), unsupervised techniques (e||||g|||| clustering, anomaly detection), natural language processing and statistical methods|||| Experience training models in a public cloud environment, using tools such as Jupyter, AWS Sagemaker|||| Ability to synthesize complex information into clear insights and translate those insights into decisions and actions|||| Ability to clearly communicate complex technical details and insights to colleagues and stakeholders|||| Knowledge of the mathematical and statistical fields that underpin data science Knowledge of systems thinking and decomposition of complex problems|||| Humble – is open to being coached, has high EQ and is self-aware Hungry – desires to get things done while honoring people, and seeks better ways to do the job Collaborative – has strong interpersonal skills; cares about and works well with teammates Experience working on an agile delivery team, using methods such as Scrum, Kanban||||Job DetailsJob Typefulltime, employeePosted 7 days ago||||",
    "KeyWords": {
      "NOUN": {
        "Scientist": "Scientist",
        "Senior": "Senior",
        "IT": "IT",
        "Data": "Data",
        "Analytics": "Analytics",
        "Team": "Team",
        "Overview": "Overview",
        "client": "client",
        "organization": "organization",
        "value": "value",
        "data": "data",
        "company": "company",
        "Wildfire": "Wildfire",
        "Safety": "Safety",
        "Program": "Program",
        "part": "part",
        "focus": "focus",
        "AI/Client": "AI/Client",
        "centric": "centric",
        "products": "products",
        "initiatives": "initiatives",
        "Remote": "Remote",
        "Inspections": "Inspections",
        "AI": "AI",
        "Enabled": "Enabled",
        "Vegetation": "Vegetation",
        "Management": "Management",
        "LiDAR": "LiDAR",
        "capabilities": "capabilities",
        "Transmission": "Transmission",
        "Line": "Line",
        "Asset": "Asset",
        "Foundation": "Foundation",
        "Electric": "Electric",
        "Distribution": "Distribution",
        "Risk": "Risk",
        "Modeling": "Modeling",
        "Cloud": "Cloud",
        "Native": "Native",
        "Foundational": "Foundational",
        "Platform": "Platform",
        "design": "design",
        "thinking": "thinking",
        "work": "work",
        "Agile": "Agile",
        "development": "development",
        "methodology": "methodology",
        "co-location": "co-location",
        "principles": "principles",
        "product": "product",
        "teams": "teams",
        "business": "business",
        "Position": "Position",
        "Summary": "Summary",
        "candidate": "candidate",
        "delivery": "delivery",
        "team": "team",
        "best-practice": "best-practice",
        "agile": "agile",
        "science": "science",
        "techniques": "techniques",
        "partners": "partners",
        "lifecycle": "lifecycle",
        "model": "model",
        "user": "user",
        "discovery": "discovery",
        "engineering": "engineering",
        "feature": "feature",
        "training": "training",
        "validation": "validation",
        "deployment": "deployment",
        "practice": "practice",
        "environment": "environment",
        "mature": "mature",
        "Responsibilities": "Responsibilities",
        "Applies": "Applies",
        "machine": "machine",
        "learning": "learning",
        "methods": "methods",
        "models": "models",
        "visualizations": "visualizations",
        "software": "software",
        "Gathers": "Gathers",
        "cleans": "cleans",
        "transforms": "transforms",
        "reduces": "reduces",
        "sources": "sources",
        "Collaborates": "Collaborates",
        "members": "members",
        "stakeholders": "stakeholders",
        "appropriate": "appropriate",
        "Shares": "Shares",
        "collaborates": "collaborates",
        "scientists": "scientists",
        "Delivers": "Delivers",
        "Education/Skills": "Education/Skills",
        "Bachelor": "Bachelor",
        "Degree": "Degree",
        "Econometrics": "Econometrics",
        "Economics": "Economics",
        "Engineering": "Engineering",
        "Mathematics": "Mathematics",
        "Applied": "Applied",
        "Sciences": "Sciences",
        "Statistics": "Statistics",
        "discipline": "discipline",
        "experience": "experience",
        "years": "years",
        "OR": "OR",
        "Master": "Master",
        "Doctorate": "Doctorate",
        "Desired": "Desired",
        "Education": "Education",
        "Skills": "Skills",
        "Experience": "Experience",
        "building": "building",
        "evaluation": "evaluation",
        "Knowledge": "Knowledge",
        "programming": "programming",
        "languages": "languages",
        "packages": "packages",
        "tools": "tools",
        "Python": "Python",
        "Understanding": "Understanding",
        "science/machine": "science/machine",
        "algorithms": "algorithms",
        "CNN": "CNN",
        "RNN": "RNN",
        "etc": "etc",
        "decision": "decision",
        "trees": "trees",
        "g.": "g.",
        "xgboost": "xgboost",
        "forest": "forest",
        "clustering": "clustering",
        "detection": "detection",
        "language": "language",
        "processing": "processing",
        "cloud": "cloud",
        "Jupyter": "Jupyter",
        "AWS": "AWS",
        "Sagemaker": "Sagemaker",
        "Ability": "Ability",
        "information": "information",
        "insights": "insights",
        "decisions": "decisions",
        "actions": "actions",
        "details": "details",
        "colleagues": "colleagues",
        "fields": "fields",
        "systems": "systems",
        "decomposition": "decomposition",
        "problems": "problems",
        "EQ": "EQ",
        "Hungry": "Hungry",
        "things": "things",
        "people": "people",
        "ways": "ways",
        "job": "job",
        "Collaborative": "Collaborative",
        "skills": "skills",
        "cares": "cares",
        "works": "works",
        "teammates": "teammates",
        "Scrum": "Scrum",
        "Kanban": "Kanban",
        "Job": "Job",
        "DetailsJob": "DetailsJob",
        "Typefulltime": "Typefulltime",
        "days": "days"
      },
      "VERB": {
        "focused": "focused",
        "unlocking": "unlocking",
        "support": "support",
        "focus": "focus",
        "delivering": "delivering",
        "are": "are",
        "being": "being",
        "delivered": "delivered",
        "include": "include",
        "operate": "operate",
        "is": "is",
        "apply": "apply",
        "observe": "observe",
        "work": "work",
        "help": "help",
        "deliver": "deliver",
        "seeking": "seeking",
        "will": "will",
        "join": "join",
        "following": "following",
        "participate": "participate",
        "model": "model",
        "joining": "joining",
        "existing": "existing",
        "modeling": "modeling",
        "develop": "develop",
        "including": "including",
        "manage": "manage",
        "retraining": "retraining",
        "replacing": "replacing",
        "sunsetting": "sunsetting",
        "used": "used",
        "limited": "limited",
        "using": "using",
        "synthesize": "synthesize",
        "translate": "translate",
        "communicate": "communicate",
        "underpin": "underpin",
        "thinking": "thinking",
        "coached": "coached",
        "has": "has",
        "desires": "desires",
        "get": "get",
        "done": "done",
        "honoring": "honoring",
        "seeks": "seeks",
        "do": "do",
        "working": "working",
        "employeePosted": "employeePosted"
      },
      "PRT": {
        "to": "to",
        "'s": "'s"
      },
      "ADJ": {
        "valuable": "valuable",
        "successful": "successful",
        "impactful": "impactful",
        "internal": "internal",
        "end-to-end": "end-to-end",
        "initial": "initial",
        "business-facing": "business-facing",
        "open": "open",
        "collaborative": "collaborative",
        "other": "other",
        "analytical": "analytical",
        "robust": "robust",
        "reliable": "reliable",
        "and/or": "and/or",
        "dissimilar": "dissimilar",
        "best-in-class": "best-in-class",
        "Minimum": "Minimum",
        "job-related": "job-related",
        "equivalent": "equivalent",
        "Job-related": "Job-related",
        "deep": "deep",
        "e.": "e.",
        "random": "random",
        "unsupervised": "unsupervised",
        "anomaly": "anomaly",
        "natural": "natural",
        "statistical": "statistical",
        "public": "public",
        "such": "such",
        "complex": "complex",
        "clear": "clear",
        "technical": "technical",
        "mathematical": "mathematical",
        "Humble": "Humble",
        "high": "high",
        "self-aware": "self-aware",
        "better": "better",
        "strong": "strong",
        "interpersonal": "interpersonal",
        "agile": "agile"
      }
    }
  },
  "217486312": {
    "Company": "EDI Specialists, Inc.",
    "Job Title": "Data Scientist II",
    "Job Details": "DescriptionOur client in the Bay Area is currently recruiting for aData Scientist II to join itsGlobal Merchandise Planning, Supply and Inventory Management|||| You will be a part of the Demand & Supply Planning Data Science team|||| As Data Scientist you will interact with different functions within the organization to help build strategic computational planning capabilities|||| You will implement excellent Machine Learning and Deep Learning algorithms from training to deployment along with managing complex data science workflowsDesired education and work experience: Master's/PhD degree (computer science, applied mathematics, applied statistics, data science, or similar) Overall 7+ years (with Bachelor's or Master's) or 4+ years (for PhDs) relevant (hands-on) professional experience in data science, and applied statistics, and computer science, and machine learning engineering in the field of consumer goods and tech industry and retail industry|||| Key Responsibilities: Partner with stakeholders across the organization to identify high-impact opportunities to use our data to serve our disruptive planning strategy|||| Build complex predictive models using Machine Learning and Deep Learning algorithms to substantially improve our planning process and contribute to business growth|||| Assess the potential usefulness and validity of new Client and DL approaches and data sources|||| Manipulate large databases with structured and unstructured (text, images, videos||||||||) data from our sources|||| develop proof-of-concept prototypes to prove out hypotheses|||| Manage experience with data, including complex queries, exploratory data analysis, data visualization, advanced modeling and communication of applicable insights to audiences at varying levels of technical sophistication|||| Actively and continuously contribute to our data science culture and strategy|||| Required Technical Skills: 3+ years of prior experience in a business-focused Data Scientist role 3+ years of hands-on experience analyzing data, drawing conclusions, defining recommended actions, building predictive models, and visualizing results|||| 3+ years of SQL development skills writing complex queries|||| 4+ years of experience with Python, R, Java, C++, Julia, or another widely used open-source programming language|||| 4+ years of experience deploying Machine Learning algorithms in a production environment|||| 3+ years' experience in experience in Deep Learning engineering|||| Experience in Reinforcement Machine Learning is a huge plus|||| 3+ years' experience with big data processing tools such as MapReduce, PIG, and HIVE, Hadoop, with considerable experience working with Spark|||| 3+ years of experience working with SQL and Non-SQL databases|||| 3+ years of experience with data visualization tools (D3||||js, R Shiny, Looker, Tableau or similar)|||| Experience working with cloud environments: AWS and/or Azure and/or GCP cloud platforms|||| Experience working with Linux/UNIX shell virtual machines|||| Familiarity with distributed systems (Docker, Kubernetes, Kafka, Spark) Experience using data access tools and building web application and simple UI solutions|||| Experience in Data Engineering and DevOps would be a nice to have||||Job DetailsJob Typefulltime, employeePosted 4 days ago||||",
    "KeyWords": {
      "NOUN": {
        "client": "client",
        "Bay": "Bay",
        "Area": "Area",
        "aData": "aData",
        "Scientist": "Scientist",
        "II": "II",
        "Merchandise": "Merchandise",
        "Planning": "Planning",
        "Supply": "Supply",
        "Inventory": "Inventory",
        "Management": "Management",
        "part": "part",
        "Demand": "Demand",
        "Data": "Data",
        "Science": "Science",
        "team": "team",
        "functions": "functions",
        "organization": "organization",
        "planning": "planning",
        "capabilities": "capabilities",
        "Machine": "Machine",
        "Learning": "Learning",
        "Deep": "Deep",
        "algorithms": "algorithms",
        "data": "data",
        "science": "science",
        "education": "education",
        "work": "work",
        "experience": "experience",
        "Master's/PhD": "Master's/PhD",
        "degree": "degree",
        "computer": "computer",
        "mathematics": "mathematics",
        "statistics": "statistics",
        "years": "years",
        "Bachelor": "Bachelor",
        "Master": "Master",
        "PhDs": "PhDs",
        "relevant": "relevant",
        "machine": "machine",
        "engineering": "engineering",
        "field": "field",
        "consumer": "consumer",
        "goods": "goods",
        "tech": "tech",
        "industry": "industry",
        "Responsibilities": "Responsibilities",
        "Partner": "Partner",
        "stakeholders": "stakeholders",
        "opportunities": "opportunities",
        "strategy": "strategy",
        "Build": "Build",
        "predictive": "predictive",
        "models": "models",
        "process": "process",
        "contribute": "contribute",
        "business": "business",
        "growth": "growth",
        "usefulness": "usefulness",
        "validity": "validity",
        "Client": "Client",
        "DL": "DL",
        "approaches": "approaches",
        "sources": "sources",
        "Manipulate": "Manipulate",
        "databases": "databases",
        "images": "images",
        "videos": "videos",
        "prototypes": "prototypes",
        "hypotheses": "hypotheses",
        "Manage": "Manage",
        "queries": "queries",
        "exploratory": "exploratory",
        "analysis": "analysis",
        "visualization": "visualization",
        "modeling": "modeling",
        "communication": "communication",
        "insights": "insights",
        "audiences": "audiences",
        "levels": "levels",
        "sophistication": "sophistication",
        "culture": "culture",
        "Skills": "Skills",
        "role": "role",
        "conclusions": "conclusions",
        "actions": "actions",
        "results": "results",
        "SQL": "SQL",
        "development": "development",
        "skills": "skills",
        "Python": "Python",
        "Java": "Java",
        "C++": "C++",
        "Julia": "Julia",
        "open-source": "open-source",
        "programming": "programming",
        "language": "language",
        "production": "production",
        "environment": "environment",
        "Experience": "Experience",
        "Reinforcement": "Reinforcement",
        "plus": "plus",
        "processing": "processing",
        "tools": "tools",
        "MapReduce": "MapReduce",
        "PIG": "PIG",
        "HIVE": "HIVE",
        "Hadoop": "Hadoop",
        "Spark": "Spark",
        "Non-SQL": "Non-SQL",
        "D3": "D3",
        "js": "js",
        "Shiny": "Shiny",
        "Looker": "Looker",
        "Tableau": "Tableau",
        "environments": "environments",
        "AWS": "AWS",
        "Azure": "Azure",
        "and/or": "and/or",
        "GCP": "GCP",
        "cloud": "cloud",
        "platforms": "platforms",
        "Linux/UNIX": "Linux/UNIX",
        "machines": "machines",
        "Familiarity": "Familiarity",
        "systems": "systems",
        "Docker": "Docker",
        "Kubernetes": "Kubernetes",
        "Kafka": "Kafka",
        "access": "access",
        "building": "building",
        "web": "web",
        "application": "application",
        "UI": "UI",
        "solutions": "solutions",
        "Engineering": "Engineering",
        "DevOps": "DevOps",
        "Job": "Job",
        "DetailsJob": "DetailsJob",
        "Typefulltime": "Typefulltime",
        "days": "days"
      },
      "VERB": {
        "recruiting": "recruiting",
        "join": "join",
        "will": "will",
        "be": "be",
        "interact": "interact",
        "help": "help",
        "build": "build",
        "implement": "implement",
        "training": "training",
        "deployment": "deployment",
        "managing": "managing",
        "workflowsDesired": "workflowsDesired",
        "applied": "applied",
        "learning": "learning",
        "identify": "identify",
        "use": "use",
        "serve": "serve",
        "using": "using",
        "improve": "improve",
        "Assess": "Assess",
        "develop": "develop",
        "prove": "prove",
        "including": "including",
        "advanced": "advanced",
        "varying": "varying",
        "contribute": "contribute",
        "Required": "Required",
        "analyzing": "analyzing",
        "drawing": "drawing",
        "defining": "defining",
        "building": "building",
        "visualizing": "visualizing",
        "writing": "writing",
        "used": "used",
        "deploying": "deploying",
        "is": "is",
        "working": "working",
        "and/or": "and/or",
        "shell": "shell",
        "would": "would",
        "have": "have",
        "employeePosted": "employeePosted"
      },
      "PRT": {
        "to": "to",
        "'s": "'s",
        "out": "out"
      },
      "ADJ": {
        "different": "different",
        "strategic": "strategic",
        "computational": "computational",
        "excellent": "excellent",
        "complex": "complex",
        "similar": "similar",
        "Overall": "Overall",
        "hands-on": "hands-on",
        "professional": "professional",
        "applied": "applied",
        "retail": "retail",
        "Key": "Key",
        "high-impact": "high-impact",
        "disruptive": "disruptive",
        "potential": "potential",
        "new": "new",
        "large": "large",
        "structured": "structured",
        "unstructured": "unstructured",
        "text": "text",
        "proof-of-concept": "proof-of-concept",
        "applicable": "applicable",
        "technical": "technical",
        "Technical": "Technical",
        "prior": "prior",
        "business-focused": "business-focused",
        "recommended": "recommended",
        "predictive": "predictive",
        "huge": "huge",
        "big": "big",
        "such": "such",
        "considerable": "considerable",
        "cloud": "cloud",
        "virtual": "virtual",
        "distributed": "distributed",
        "simple": "simple",
        "nice": "nice"
      },
      "NUM": {
        "4+": "4+",
        "3+": "3+"
      }
    }
  },
  "217565506": {
    "Company": "Skyrocket Ventures",
    "Job Title": "Sr. to Lead Backend Software Engineer - Augmented Reality",
    "Job Details": "DescriptionSkyrocket Ventures is a recruiting firm for hundreds of high growth technology companies that range from industry leaders to top-tier startups||||  This opportunity is with one of our client companies for a full-time permanent hire||||  Please only apply if you are authorized to work in the U||||S||||Please note that even if this job is not a perfect match, we encourage you to apply as long as it is in the ballpark||||  Companies are often flexible in hiring candidates who do not perfectly fit their written job description, as long as the most important qualifications are there and the candidate is good in general||||Most of the jobs we are recruiting for are not posted online, so if you would like to know of all the opportunities we have that match your interests and qualifications, then please get in touch with us||||Thank you!Matthew StrassbergRecruiting DirectorSkyrocket VenturesFeel free to check out testimonials from some of our many candidates/clients here:http://www||||linkedin||||com/in/mstrassbergSr|||| to Lead Backend Software Engineer - Augmented Reality CompanyOakland, CA (you can work from home up to 2x/week)This company is in the augmented reality space, and is revolutionizing the retail industry with its technology|||| The company's product is used by millions of people all over the world|||| The company has raised a large round of funding from top tier investors, has about 50 employees, and is rapidly growing||||Job Responsibilities:- Implementing complex software based on project requirements, technical designs and best practices||||- Reviewing designs and collaborating to solve clients' problems||||- Developing, enhancing and sustaining novel solutions to optimize the customer experience||||- Contribute to design and architecture in order to improve throughput, efficiency, and fidelity||||- Developing consumer-facing API’s and services||||- Designing and architecting new software services for the company's growing business||||- Working within an agile development environment||||Qualifications:- A Bachelor's degree in computer science or equivalent experience|||| Solid CS fundamentals||||- At least 4 years, preferably 6 or more years of backend software engineering experience using Python||||- Experience with Linux||||- Experience with AWS||||- Understanding of internet fundamentals including networks protocols, queuing, and load balancing||||- Solid verbal and written communication skills||||- Experience building scalable distributed systemsNice to have:- Experience with Django and/or Flask||||- Experience with computer vision, augmented reality, and/or rendering||||- Understanding of hardware systems||||- Experience leading and/or mentoring colleagues||||- Experience in C or C++||||- Experience with OpenCV||||- Experience with OpenGL||||Did you like this job or want to see more?  All of our online job postings can be found on these sites:https://www||||dice||||com/company/10366547https://www||||monster||||com/jobs/c-skyrocket-ventures||||aspxhttps://www||||linkedin||||com/jobs/skyrocket-ventures-jobsFollow us on Instagram here:https://www||||instagram||||com/skyrocketventuresFollow us on LinkedIn here:https://www||||linkedin||||com/company/skyrocket-venturesJob DetailsJob Typefulltime, employeePosted 13 days ago||||",
    "KeyWords": {
      "NOUN": {
        "Ventures": "Ventures",
        "recruiting": "recruiting",
        "firm": "firm",
        "hundreds": "hundreds",
        "growth": "growth",
        "technology": "technology",
        "companies": "companies",
        "industry": "industry",
        "leaders": "leaders",
        "startups": "startups",
        "opportunity": "opportunity",
        "client": "client",
        "hire": "hire",
        "Please": "Please",
        "U.": "U.",
        "S.": "S.",
        "job": "job",
        "match": "match",
        "ballpark": "ballpark",
        "Companies": "Companies",
        "candidates": "candidates",
        "description": "description",
        "qualifications": "qualifications",
        "candidate": "candidate",
        "jobs": "jobs",
        "online": "online",
        "opportunities": "opportunities",
        "interests": "interests",
        "touch": "touch",
        "Matthew": "Matthew",
        "DirectorSkyrocket": "DirectorSkyrocket",
        "VenturesFeel": "VenturesFeel",
        "testimonials": "testimonials",
        "candidates/clients": "candidates/clients",
        "http": "http",
        "//www": "//www",
        "linkedin": "linkedin",
        "com/in/mstrassbergSr": "com/in/mstrassbergSr",
        "Backend": "Backend",
        "Software": "Software",
        "Engineer": "Engineer",
        "Reality": "Reality",
        "CompanyOakland": "CompanyOakland",
        "CA": "CA",
        "home": "home",
        "company": "company",
        "reality": "reality",
        "space": "space",
        "product": "product",
        "millions": "millions",
        "people": "people",
        "world": "world",
        "round": "round",
        "funding": "funding",
        "tier": "tier",
        "investors": "investors",
        "employees": "employees",
        "Job": "Job",
        "Responsibilities": "Responsibilities",
        "software": "software",
        "project": "project",
        "requirements": "requirements",
        "designs": "designs",
        "practices": "practices",
        "clients": "clients",
        "problems": "problems",
        "solutions": "solutions",
        "customer": "customer",
        "experience": "experience",
        "Contribute": "Contribute",
        "order": "order",
        "throughput": "throughput",
        "efficiency": "efficiency",
        "fidelity": "fidelity",
        "API": "API",
        "services": "services",
        "Designing": "Designing",
        "business": "business",
        "agile": "agile",
        "development": "development",
        "environment": "environment",
        "Qualifications": "Qualifications",
        "Bachelor": "Bachelor",
        "degree": "degree",
        "computer": "computer",
        "science": "science",
        "Solid": "Solid",
        "CS": "CS",
        "fundamentals": "fundamentals",
        "years": "years",
        "backend": "backend",
        "engineering": "engineering",
        "Python": "Python",
        "Experience": "Experience",
        "Linux": "Linux",
        "AWS": "AWS",
        "Understanding": "Understanding",
        "networks": "networks",
        "protocols": "protocols",
        "load": "load",
        "balancing": "balancing",
        "communication": "communication",
        "skills": "skills",
        "building": "building",
        "systemsNice": "systemsNice",
        "Django": "Django",
        "and/or": "and/or",
        "Flask": "Flask",
        "vision": "vision",
        "rendering": "rendering",
        "hardware": "hardware",
        "systems": "systems",
        "colleagues": "colleagues",
        "C++": "C++",
        "OpenCV": "OpenCV",
        "OpenGL": "OpenGL",
        "Did": "Did",
        "postings": "postings",
        "sites": "sites",
        "https": "https",
        "dice": "dice",
        "com/company/10366547https": "com/company/10366547https",
        "monster": "monster",
        "com/jobs/c-skyrocket-ventures": "com/jobs/c-skyrocket-ventures",
        "aspxhttps": "aspxhttps",
        "Instagram": "Instagram",
        "instagram": "instagram",
        "LinkedIn": "LinkedIn",
        "DetailsJob": "DetailsJob",
        "Typefulltime": "Typefulltime",
        "days": "days"
      },
      "VERB": {
        "range": "range",
        "is": "is",
        "apply": "apply",
        "are": "are",
        "authorized": "authorized",
        "work": "work",
        "note": "note",
        "encourage": "encourage",
        "hiring": "hiring",
        "do": "do",
        "fit": "fit",
        "written": "written",
        "recruiting": "recruiting",
        "posted": "posted",
        "would": "would",
        "like": "like",
        "know": "know",
        "have": "have",
        "match": "match",
        "please": "please",
        "get": "get",
        "Thank": "Thank",
        "StrassbergRecruiting": "StrassbergRecruiting",
        "check": "check",
        "Lead": "Lead",
        "can": "can",
        "revolutionizing": "revolutionizing",
        "used": "used",
        "has": "has",
        "raised": "raised",
        "growing": "growing",
        "Implementing": "Implementing",
        "based": "based",
        "Reviewing": "Reviewing",
        "collaborating": "collaborating",
        "solve": "solve",
        "Developing": "Developing",
        "enhancing": "enhancing",
        "sustaining": "sustaining",
        "optimize": "optimize",
        "design": "design",
        "architecture": "architecture",
        "improve": "improve",
        "architecting": "architecting",
        "Working": "Working",
        "using": "using",
        "including": "including",
        "queuing": "queuing",
        "augmented": "augmented",
        "leading": "leading",
        "mentoring": "mentoring",
        "want": "want",
        "see": "see",
        "be": "be",
        "found": "found",
        "com/skyrocketventuresFollow": "com/skyrocketventuresFollow",
        "employeePosted": "employeePosted"
      },
      "ADJ": {
        "top-tier": "top-tier",
        "full-time": "full-time",
        "permanent": "permanent",
        "perfect": "perfect",
        "flexible": "flexible",
        "important": "important",
        "good": "good",
        "general": "general",
        "Most": "Most",
        "free": "free",
        "many": "many",
        "Augmented": "Augmented",
        "augmented": "augmented",
        "retail": "retail",
        "large": "large",
        "top": "top",
        "complex": "complex",
        "technical": "technical",
        "best": "best",
        "novel": "novel",
        "consumer-facing": "consumer-facing",
        "new": "new",
        "equivalent": "equivalent",
        "least": "least",
        "more": "more",
        "internet": "internet",
        "Solid": "Solid",
        "verbal": "verbal",
        "scalable": "scalable",
        "distributed": "distributed",
        "and/or": "and/or",
        "online": "online",
        "com/jobs/skyrocket-ventures-jobsFollow": "com/jobs/skyrocket-ventures-jobsFollow",
        "com/company/skyrocket-venturesJob": "com/company/skyrocket-venturesJob"
      },
      "PRT": {
        "to": "to",
        "out": "out",
        "'s": "'s"
      },
      "NUM": {
        "13": "13",
        "50": "50",
        "2x/week": "2x/week"
      }
    }
  },
  "217565623": {
    "Company": "Skyrocket Ventures",
    "Job Title": "Sr. to Lead iOS Engineer - Augmented Reality",
    "Job Details": "DescriptionSkyrocket Ventures is a recruiting firm for hundreds of high growth technology companies that range from industry leaders to top-tier startups||||  This opportunity is with one of our client companies for a full-time permanent hire||||  Please only apply if you are authorized to work in the U||||S||||Please note that even if this job is not a perfect match, we encourage you to apply as long as it is in the ballpark||||  Companies are often flexible in hiring candidates who do not perfectly fit their written job description, as long as the most important qualifications are there and the candidate is good in general||||Most of the jobs we are recruiting for are not posted online, so if you would like to know of all the opportunities we have that match your interests and qualifications, then please get in touch with us||||Thank you!Matthew StrassbergRecruiting DirectorSkyrocket VenturesFeel free to check out testimonials from some of our many candidates/clients here:http://www||||linkedin||||com/in/mstrassbergSr|||| to Lead iOS Engineer - Augmented Reality CompanyOakland, CA (you can work from home up to 2x/week)This company is in the augmented reality space, and is revolutionizing the retail industry with its technology|||| The company's product is used by millions of people all over the world|||| The company has raised a large round of funding from top tier investors, has about 50 employees, and is rapidly growing||||Job Responsibilities:- Working with a team of a few other iOS Engineers||||- Developing innovative consumer mobile products||||- Designing and developing the company's iOS software for multiple platforms including iPhone and iPad||||- Building iOS SDKs and consumer-facing applications||||- Working within an agile development environment||||- Prototyping new features||||Qualifications:- A Bachelor's degree in Computer Science or equivalent experience|||| Solid CS fundamentals||||- At least 4 years (preferably more) of iOS experience||||- Understanding of mobile architecture||||- Understanding of user interface design||||- Published app(s) in the App Store||||- Solid written and verbal communication skills||||Strongly preferred:- Expertise in Swift||||Nice to have:- Experience leading and mentoring colleagues||||- Experience with C and/or C++||||- Experience with Python||||- Experience with OpenGL||||- Experience with Android||||Did you like this job or want to see more?  All of our online job postings can be found on these sites:https://www||||dice||||com/company/10366547https://www||||monster||||com/jobs/c-skyrocket-ventures||||aspxhttps://www||||linkedin||||com/jobs/skyrocket-ventures-jobsFollow us on Instagram here:https://www||||instagram||||com/skyrocketventuresFollow us on LinkedIn here:https://www||||linkedin||||com/company/skyrocket-venturesJob DetailsJob Typefulltime, employeePosted 13 days ago||||",
    "KeyWords": {
      "NOUN": {
        "Ventures": "Ventures",
        "recruiting": "recruiting",
        "firm": "firm",
        "hundreds": "hundreds",
        "growth": "growth",
        "technology": "technology",
        "companies": "companies",
        "industry": "industry",
        "leaders": "leaders",
        "startups": "startups",
        "opportunity": "opportunity",
        "client": "client",
        "hire": "hire",
        "Please": "Please",
        "U.": "U.",
        "S.": "S.",
        "job": "job",
        "match": "match",
        "ballpark": "ballpark",
        "Companies": "Companies",
        "candidates": "candidates",
        "description": "description",
        "qualifications": "qualifications",
        "candidate": "candidate",
        "jobs": "jobs",
        "online": "online",
        "opportunities": "opportunities",
        "interests": "interests",
        "touch": "touch",
        "Matthew": "Matthew",
        "DirectorSkyrocket": "DirectorSkyrocket",
        "VenturesFeel": "VenturesFeel",
        "testimonials": "testimonials",
        "candidates/clients": "candidates/clients",
        "http": "http",
        "//www": "//www",
        "linkedin": "linkedin",
        "com/in/mstrassbergSr": "com/in/mstrassbergSr",
        "iOS": "iOS",
        "Engineer": "Engineer",
        "Reality": "Reality",
        "CompanyOakland": "CompanyOakland",
        "CA": "CA",
        "home": "home",
        "company": "company",
        "reality": "reality",
        "space": "space",
        "product": "product",
        "millions": "millions",
        "people": "people",
        "world": "world",
        "round": "round",
        "funding": "funding",
        "tier": "tier",
        "investors": "investors",
        "employees": "employees",
        "Job": "Job",
        "Responsibilities": "Responsibilities",
        "team": "team",
        "Engineers": "Engineers",
        "consumer": "consumer",
        "mobile": "mobile",
        "products": "products",
        "Designing": "Designing",
        "software": "software",
        "platforms": "platforms",
        "iPhone": "iPhone",
        "iPad": "iPad",
        "Building": "Building",
        "SDKs": "SDKs",
        "applications": "applications",
        "agile": "agile",
        "development": "development",
        "environment": "environment",
        "features": "features",
        "Qualifications": "Qualifications",
        "Bachelor": "Bachelor",
        "degree": "degree",
        "Computer": "Computer",
        "Science": "Science",
        "experience": "experience",
        "Solid": "Solid",
        "CS": "CS",
        "fundamentals": "fundamentals",
        "years": "years",
        "Understanding": "Understanding",
        "architecture": "architecture",
        "interface": "interface",
        "design": "design",
        "app": "app",
        "App": "App",
        "Store": "Store",
        "communication": "communication",
        "skills": "skills",
        "Expertise": "Expertise",
        "Swift": "Swift",
        "Nice": "Nice",
        "Experience": "Experience",
        "colleagues": "colleagues",
        "and/or": "and/or",
        "C++": "C++",
        "Python": "Python",
        "OpenGL": "OpenGL",
        "Android": "Android",
        "Did": "Did",
        "postings": "postings",
        "sites": "sites",
        "https": "https",
        "dice": "dice",
        "com/company/10366547https": "com/company/10366547https",
        "monster": "monster",
        "com/jobs/c-skyrocket-ventures": "com/jobs/c-skyrocket-ventures",
        "aspxhttps": "aspxhttps",
        "Instagram": "Instagram",
        "instagram": "instagram",
        "LinkedIn": "LinkedIn",
        "DetailsJob": "DetailsJob",
        "Typefulltime": "Typefulltime",
        "days": "days"
      },
      "VERB": {
        "range": "range",
        "is": "is",
        "apply": "apply",
        "are": "are",
        "authorized": "authorized",
        "work": "work",
        "note": "note",
        "encourage": "encourage",
        "hiring": "hiring",
        "do": "do",
        "fit": "fit",
        "written": "written",
        "recruiting": "recruiting",
        "posted": "posted",
        "would": "would",
        "like": "like",
        "know": "know",
        "have": "have",
        "match": "match",
        "please": "please",
        "get": "get",
        "Thank": "Thank",
        "StrassbergRecruiting": "StrassbergRecruiting",
        "check": "check",
        "Lead": "Lead",
        "can": "can",
        "revolutionizing": "revolutionizing",
        "used": "used",
        "has": "has",
        "raised": "raised",
        "growing": "growing",
        "Working": "Working",
        "Developing": "Developing",
        "developing": "developing",
        "including": "including",
        "Prototyping": "Prototyping",
        "Published": "Published",
        "preferred": "preferred",
        "mentoring": "mentoring",
        "want": "want",
        "see": "see",
        "be": "be",
        "found": "found",
        "com/skyrocketventuresFollow": "com/skyrocketventuresFollow",
        "employeePosted": "employeePosted"
      },
      "ADJ": {
        "top-tier": "top-tier",
        "full-time": "full-time",
        "permanent": "permanent",
        "perfect": "perfect",
        "flexible": "flexible",
        "important": "important",
        "good": "good",
        "general": "general",
        "Most": "Most",
        "free": "free",
        "many": "many",
        "Augmented": "Augmented",
        "augmented": "augmented",
        "retail": "retail",
        "large": "large",
        "top": "top",
        "few": "few",
        "other": "other",
        "innovative": "innovative",
        "multiple": "multiple",
        "consumer-facing": "consumer-facing",
        "new": "new",
        "equivalent": "equivalent",
        "least": "least",
        "iOS": "iOS",
        "mobile": "mobile",
        "user": "user",
        "Solid": "Solid",
        "verbal": "verbal",
        "leading": "leading",
        "more": "more",
        "online": "online",
        "com/jobs/skyrocket-ventures-jobsFollow": "com/jobs/skyrocket-ventures-jobsFollow",
        "com/company/skyrocket-venturesJob": "com/company/skyrocket-venturesJob"
      },
      "PRT": {
        "to": "to",
        "out": "out",
        "'s": "'s"
      },
      "NUM": {
        "13": "13",
        "50": "50",
        "2x/week": "2x/week"
      }
    }
  },
  "217606968": {
    "Company": "Ascent Services Group",
    "Job Title": "Software Architect",
    "Job Details": "DescriptionSoftware ArchitectSSF, CAInital 1-year contract (w2 only)- MAY extend up to 3yearsSeeking a Software Architect reporting to the AI Infrastructure and Imaging Lead to help the team within Early Clinical Development|||| |||| The AI team applies machine learning innovations to find solutions for supporting clinical and operational decisions, personalized medicine and patient response and safety based on multi-modal datasets including clinical, radiology, genomics, etc datasets|||| The Software Architect will collaborate with the rest of the AI team and the external collaborators in implementing software engineering best practices to build maintainable, and performant code base as well as coaching other team members to build a strong software engineering culture||||Responsibilities Authoring and presenting design documents for various software and AI projects Hands-on implementation of key software pieces Ensuring high quality, maintainable, tested code base  Coaching various team members Presenting and implementing best practices in the AI team Overseeing project execution with external engineering contractors Represent the department in AI in meetings with external and internal stakeholdersRequirements Proficiency in Python|||| At least 8 years of industry experience  Proficiency in at least one other programming language, C++, Java, Rust, etc   Demonstrated proficiency in Linux systems, and hands-on experience with cloud systems Demonstrated proficiency with container technologies Demonstrated proficiency in agile software development Demonstrated proficiency in implementing CI/CD systemsPreferred additional requirements Demonstrated proficiency using TensorFlow and/or PyTorch is a strong plus Understanding and hands-on experience with distributed systems is a strong plusEducation Degree in a relevant technical field such as Statistics, Mathematics, Computer Science 8+ yrs of industry applied machine learning experienceJob DetailsJob Typefulltime, employeePosted 11 days ago||||",
    "KeyWords": {
      "NOUN": {
        "ArchitectSSF": "ArchitectSSF",
        "CAInital": "CAInital",
        "contract": "contract",
        "MAY": "MAY",
        "Software": "Software",
        "Architect": "Architect",
        "reporting": "reporting",
        "AI": "AI",
        "Infrastructure": "Infrastructure",
        "Imaging": "Imaging",
        "Lead": "Lead",
        "team": "team",
        "Early": "Early",
        "Clinical": "Clinical",
        "Development": "Development",
        "applies": "applies",
        "machine": "machine",
        "innovations": "innovations",
        "solutions": "solutions",
        "decisions": "decisions",
        "medicine": "medicine",
        "response": "response",
        "safety": "safety",
        "datasets": "datasets",
        "radiology": "radiology",
        "genomics": "genomics",
        "rest": "rest",
        "collaborators": "collaborators",
        "software": "software",
        "engineering": "engineering",
        "practices": "practices",
        "code": "code",
        "base": "base",
        "members": "members",
        "culture": "culture",
        "Responsibilities": "Responsibilities",
        "Authoring": "Authoring",
        "design": "design",
        "documents": "documents",
        "projects": "projects",
        "Hands-on": "Hands-on",
        "implementation": "implementation",
        "pieces": "pieces",
        "Ensuring": "Ensuring",
        "quality": "quality",
        "Coaching": "Coaching",
        "Overseeing": "Overseeing",
        "project": "project",
        "execution": "execution",
        "contractors": "contractors",
        "department": "department",
        "meetings": "meetings",
        "stakeholdersRequirements": "stakeholdersRequirements",
        "Proficiency": "Proficiency",
        "Python": "Python",
        "years": "years",
        "industry": "industry",
        "experience": "experience",
        "language": "language",
        "C++": "C++",
        "Java": "Java",
        "Rust": "Rust",
        "Demonstrated": "Demonstrated",
        "proficiency": "proficiency",
        "Linux": "Linux",
        "systems": "systems",
        "container": "container",
        "technologies": "technologies",
        "development": "development",
        "CI/CD": "CI/CD",
        "requirements": "requirements",
        "TensorFlow": "TensorFlow",
        "and/or": "and/or",
        "PyTorch": "PyTorch",
        "plusEducation": "plusEducation",
        "Degree": "Degree",
        "field": "field",
        "Statistics": "Statistics",
        "Mathematics": "Mathematics",
        "Computer": "Computer",
        "Science": "Science",
        "yrs": "yrs",
        "DetailsJob": "DetailsJob",
        "Typefulltime": "Typefulltime",
        "days": "days"
      },
      "ADJ": {
        "clinical": "clinical",
        "operational": "operational",
        "patient": "patient",
        "multi-modal": "multi-modal",
        "external": "external",
        "maintainable": "maintainable",
        "performant": "performant",
        "other": "other",
        "strong": "strong",
        "various": "various",
        "key": "key",
        "high": "high",
        "tested": "tested",
        "best": "best",
        "internal": "internal",
        "least": "least",
        "hands-on": "hands-on",
        "cloud": "cloud",
        "agile": "agile",
        "additional": "additional",
        "Understanding": "Understanding",
        "distributed": "distributed",
        "relevant": "relevant",
        "technical": "technical",
        "such": "such",
        "experienceJob": "experienceJob"
      },
      "VERB": {
        "3yearsSeeking": "3yearsSeeking",
        "help": "help",
        "learning": "learning",
        "find": "find",
        "supporting": "supporting",
        "personalized": "personalized",
        "based": "based",
        "including": "including",
        "will": "will",
        "collaborate": "collaborate",
        "implementing": "implementing",
        "build": "build",
        "coaching": "coaching",
        "presenting": "presenting",
        "Presenting": "Presenting",
        "Represent": "Represent",
        "programming": "programming",
        "Demonstrated": "Demonstrated",
        "systemsPreferred": "systemsPreferred",
        "using": "using",
        "is": "is",
        "applied": "applied",
        "employeePosted": "employeePosted"
      },
      "PRT": {
        "to": "to"
      },
      "X": {
        "etc": "etc"
      },
      "NUM": {
        "11": "11",
        "8+": "8+"
      }
    }
  },
  "217619799": {
    "Company": "HSK Technologies Inc.",
    "Job Title": "Lead SDET with Python/ QA Lead Engineer/Solution Architect with Python @ CA",
    "Job Details": "DescriptionLead SDET with PythonLocation: San Francisco, CADuration: 12+ monthsJob description:Senior SME leading the development of solutions for testing complex systems, ensuring consistency with specified requirements agreed with both external and internal customers||||The candidate will have expert level Python coding skills (must pass a code review in the interview)Required skills:10+ years proven experience as a QA Lead Engineer/Solution Architect on large-scale testing accountsIn-depth knowledge of one or more technical specializations including; quality engineering, release management, test environment management, test automation, test data management, testing approaches and test execution, performance engineering, development operations||||Experience in architecting, implementing solutions/frameworks for front end and APIsExperience using Web Service Testing ToolsExperience using test management tools such as JiraExperience with Source Code Management Tools (e||||g|||| Git, TFS, RTC)Knowledge of Relational Database Management (Oracle, SQL, MySQL) SQL and Data Validation are essentialUnderstanding of Performance Testing, Security, Accessibility and Infrastructure Testing would be good to haveKnowledge of mobile automation tools||||Awareness of testing approaches, practices, techniques, and methodologies to help design the overall testing solutionWell-versed in continuous integration, continuous delivery, and continuous testing Reach me on Direct: 732-481-1563 || Akhila@hsktechnologies||||net  Job DetailsJob Typefulltime, employeePosted 11 days ago||||",
    "KeyWords": {
      "NOUN": {
        "SDET": "SDET",
        "PythonLocation": "PythonLocation",
        "San": "San",
        "Francisco": "Francisco",
        "CADuration": "CADuration",
        "description": "description",
        "SME": "SME",
        "development": "development",
        "solutions": "solutions",
        "systems": "systems",
        "consistency": "consistency",
        "requirements": "requirements",
        "customers": "customers",
        "candidate": "candidate",
        "level": "level",
        "Python": "Python",
        "skills": "skills",
        "code": "code",
        "review": "review",
        "interview": "interview",
        "years": "years",
        "QA": "QA",
        "Lead": "Lead",
        "Engineer/Solution": "Engineer/Solution",
        "Architect": "Architect",
        "knowledge": "knowledge",
        "specializations": "specializations",
        "quality": "quality",
        "engineering": "engineering",
        "release": "release",
        "management": "management",
        "environment": "environment",
        "test": "test",
        "automation": "automation",
        "data": "data",
        "approaches": "approaches",
        "execution": "execution",
        "performance": "performance",
        "operations": "operations",
        "Experience": "Experience",
        "architecting": "architecting",
        "solutions/frameworks": "solutions/frameworks",
        "end": "end",
        "APIsExperience": "APIsExperience",
        "Web": "Web",
        "Service": "Service",
        "Testing": "Testing",
        "ToolsExperience": "ToolsExperience",
        "tools": "tools",
        "JiraExperience": "JiraExperience",
        "Source": "Source",
        "Code": "Code",
        "Management": "Management",
        "Tools": "Tools",
        "g.": "g.",
        "Git": "Git",
        "TFS": "TFS",
        "RTC": "RTC",
        "Knowledge": "Knowledge",
        "Relational": "Relational",
        "Database": "Database",
        "Oracle": "Oracle",
        "SQL": "SQL",
        "MySQL": "MySQL",
        "Data": "Data",
        "Validation": "Validation",
        "Performance": "Performance",
        "Security": "Security",
        "Accessibility": "Accessibility",
        "Infrastructure": "Infrastructure",
        "Awareness": "Awareness",
        "practices": "practices",
        "techniques": "techniques",
        "methodologies": "methodologies",
        "integration": "integration",
        "delivery": "delivery",
        "Reach": "Reach",
        "||": "||",
        "Akhila": "Akhila",
        "hsktechnologies": "hsktechnologies",
        "Job": "Job",
        "DetailsJob": "DetailsJob",
        "Typefulltime": "Typefulltime",
        "days": "days"
      },
      "NUM": {
        "11": "11",
        "one": "one"
      },
      "ADJ": {
        "Senior": "Senior",
        "complex": "complex",
        "specified": "specified",
        "external": "external",
        "internal": "internal",
        "expert": "expert",
        "skills:10+": "skills:10+",
        "large-scale": "large-scale",
        "accountsIn-depth": "accountsIn-depth",
        "more": "more",
        "technical": "technical",
        "front": "front",
        "such": "such",
        "e.": "e.",
        "good": "good",
        "mobile": "mobile",
        "overall": "overall",
        "solutionWell-versed": "solutionWell-versed",
        "continuous": "continuous",
        "Direct": "Direct",
        "732-481-1563": "732-481-1563",
        "net": "net"
      },
      "VERB": {
        "testing": "testing",
        "ensuring": "ensuring",
        "agreed": "agreed",
        "will": "will",
        "have": "have",
        "coding": "coding",
        "must": "must",
        "pass": "pass",
        "Required": "Required",
        "including": "including",
        "test": "test",
        "implementing": "implementing",
        "using": "using",
        "are": "are",
        "essentialUnderstanding": "essentialUnderstanding",
        "would": "would",
        "be": "be",
        "haveKnowledge": "haveKnowledge",
        "help": "help",
        "design": "design",
        "employeePosted": "employeePosted"
      },
      "PRT": {
        "to": "to"
      }
    }
  },
  "217655764": {
    "Company": "Cognizant",
    "Job Title": "DevOps Engineer",
    "Job Details": "DescriptionCognizant is always looking for top talent||||  We are searching for candidates to fill future needs within the business|||| This job posting represents potential future employment opportunities with Cognizant||||  Although the position is not currently available, we want to provide you with the opportunity to express your interest in future employment opportunities with Cognizant||||  If a job opportunity that you may be qualified for becomes available in the future, we will notify you||||  At that time you can determine whether you would like to apply for the specific open position||||  Thank you for your interest in Cognizant career opportunities||||   Lead DevOps Engineer    Lead DevOps Engineer is responsible for supporting the day-to-day development operations, build CI/CD systems using tools like Rally, GitHub, Jenkins, Sonar, Build tools,XL deploy, ECS, Docker and AWS Key Responsibilities Design, lead and build an automated deployment tool set and infrastructure including environments, code management, CI and CD process Help define and set best practices for code management, build, deploy and release across multiple teams/products in CI /CD model using ECS, Docker and AWS|||| Work closely with the software development team and other functional groups to develop and provide a robust, flexible and scalable platform Skills and Requirements 7+ Years of Experience as Devops Engineer in creating CI/CD pipelines for various technologies|||| Code management best practices such as branching, merging, and integration strategies|||| 3 + Years of experience in Containerization platforms such as Docker, Kubernetes|||| 3+ years of experience in using Amazon services like AMIs,Route53,VPC,EC2,EFS,ELB,ALB,SES,CloudWatch,ECS,EMR,Datapipelines,Lamda etc|||| 3+ years of experience in using at least one of the configuration management tools like Chef,Puppet or Ansible|||| 2+ years of experience in PCF|||| 2+ years of experience in using Terraform or Cloud formation|||| 2+ years of administrative proficiency on Windows, Unix systems Linux (CentOS, or other flavor) Exceptional scripting experience (Groovy, Python, etc||||)   Job DetailsJob Typefulltime, employeePosted 7 days ago||||",
    "KeyWords": {
      "NOUN": {
        "talent": "talent",
        "candidates": "candidates",
        "needs": "needs",
        "business": "business",
        "job": "job",
        "employment": "employment",
        "opportunities": "opportunities",
        "Cognizant": "Cognizant",
        "position": "position",
        "opportunity": "opportunity",
        "interest": "interest",
        "becomes": "becomes",
        "future": "future",
        "time": "time",
        "Thank": "Thank",
        "career": "career",
        "DevOps": "DevOps",
        "Engineer": "Engineer",
        "Lead": "Lead",
        "development": "development",
        "operations": "operations",
        "CI/CD": "CI/CD",
        "systems": "systems",
        "tools": "tools",
        "Rally": "Rally",
        "GitHub": "GitHub",
        "Jenkins": "Jenkins",
        "Sonar": "Sonar",
        "Build": "Build",
        "XL": "XL",
        "deploy": "deploy",
        "ECS": "ECS",
        "Docker": "Docker",
        "AWS": "AWS",
        "Key": "Key",
        "Responsibilities": "Responsibilities",
        "Design": "Design",
        "lead": "lead",
        "deployment": "deployment",
        "tool": "tool",
        "infrastructure": "infrastructure",
        "environments": "environments",
        "code": "code",
        "management": "management",
        "CI": "CI",
        "CD": "CD",
        "process": "process",
        "Help": "Help",
        "define": "define",
        "set": "set",
        "practices": "practices",
        "release": "release",
        "teams/products": "teams/products",
        "/CD": "/CD",
        "model": "model",
        "Work": "Work",
        "software": "software",
        "team": "team",
        "groups": "groups",
        "platform": "platform",
        "Skills": "Skills",
        "Requirements": "Requirements",
        "Years": "Years",
        "Experience": "Experience",
        "Devops": "Devops",
        "pipelines": "pipelines",
        "technologies": "technologies",
        "Code": "Code",
        "branching": "branching",
        "merging": "merging",
        "integration": "integration",
        "strategies": "strategies",
        "experience": "experience",
        "Containerization": "Containerization",
        "platforms": "platforms",
        "Kubernetes": "Kubernetes",
        "years": "years",
        "Amazon": "Amazon",
        "services": "services",
        "AMIs": "AMIs",
        "Route53": "Route53",
        "VPC": "VPC",
        "EC2": "EC2",
        "EFS": "EFS",
        "ELB": "ELB",
        "ALB": "ALB",
        "SES": "SES",
        "CloudWatch": "CloudWatch",
        "EMR": "EMR",
        "Datapipelines": "Datapipelines",
        "Lamda": "Lamda",
        "configuration": "configuration",
        "Chef": "Chef",
        "Puppet": "Puppet",
        "Ansible": "Ansible",
        "PCF": "PCF",
        "Terraform": "Terraform",
        "Cloud": "Cloud",
        "formation": "formation",
        "proficiency": "proficiency",
        "Windows": "Windows",
        "Unix": "Unix",
        "Linux": "Linux",
        "CentOS": "CentOS",
        "flavor": "flavor",
        "Exceptional": "Exceptional",
        "Groovy": "Groovy",
        "Python": "Python",
        "Job": "Job",
        "DetailsJob": "DetailsJob",
        "Typefulltime": "Typefulltime",
        "days": "days"
      },
      "VERB": {
        "looking": "looking",
        "are": "are",
        "searching": "searching",
        "fill": "fill",
        "posting": "posting",
        "represents": "represents",
        "is": "is",
        "want": "want",
        "provide": "provide",
        "express": "express",
        "may": "may",
        "be": "be",
        "qualified": "qualified",
        "will": "will",
        "notify": "notify",
        "can": "can",
        "determine": "determine",
        "would": "would",
        "like": "like",
        "apply": "apply",
        "supporting": "supporting",
        "build": "build",
        "using": "using",
        "set": "set",
        "including": "including",
        "develop": "develop",
        "creating": "creating",
        "scripting": "scripting",
        "employeePosted": "employeePosted"
      },
      "ADJ": {
        "future": "future",
        "potential": "potential",
        "available": "available",
        "specific": "specific",
        "open": "open",
        "Lead": "Lead",
        "responsible": "responsible",
        "day-to-day": "day-to-day",
        "automated": "automated",
        "best": "best",
        "multiple": "multiple",
        "other": "other",
        "functional": "functional",
        "robust": "robust",
        "flexible": "flexible",
        "scalable": "scalable",
        "various": "various",
        "such": "such",
        "least": "least",
        "administrative": "administrative"
      },
      "PRT": {
        "to": "to"
      },
      "NUM": {
        "3+": "3+",
        "one": "one",
        "2+": "2+"
      },
      "X": {
        "etc": "etc"
      }
    }
  },
  "217664997": {
    "Company": "Collabera",
    "Job Title": "Senior Python Developer",
    "Job Details": "DescriptionSan Francisco, CaliforniaSkills : Python,Javascript,PostgresSQLDescription : Senior Python DeveloperAre you interested in working on a next generation e-commerce platform that is revolutionizing the consumer experience? How about being part of a company that is highly profitable and a verified Unicorn? Does building out a platform with top-tier SF leadership sound interesting? If you are well-versed in Python, Rub||||y or Java and have experience building out scalable systems, read on! We are growing exponentially, have an amazing team, and are looking for mid to principal engineers! What you'll be working on:Building and creating a functional e-commerce platformUtilize cutting edge technologies to build a next generation consumer experienceProvide Leadership and mentoring to the team||||You must have:BSCS in Computer Science or a related field, or equivalent industry experienceStrong at software architecture and designStrong at either python or another language like Rub||||y, java, or C++|||| ideally strong at scripting and compiled languages||||Strong experience with databases (relational or not)Exposure to large scale, in-production environments in the past (consumer websites)Able to take on DevOps or Systems tasks ideally||||PlusesExperience with Kubernetes / Docker / ContainerizationBenefits:Industry Leading Compensation PackageStrong benefits package+vacation time + stockOne day work from homeGreat office environment, catered lunches, plenty of other perks!If you are ready to take this challenge, please send your resume to alexander||||harrington@collabera||||comJob DetailsJob Typefulltime, contractPosted 7 days ago||||",
    "KeyWords": {
      "NOUN": {
        "Francisco": "Francisco",
        "CaliforniaSkills": "CaliforniaSkills",
        "Python": "Python",
        "Javascript": "Javascript",
        "PostgresSQLDescription": "PostgresSQLDescription",
        "DeveloperAre": "DeveloperAre",
        "generation": "generation",
        "platform": "platform",
        "consumer": "consumer",
        "experience": "experience",
        "part": "part",
        "company": "company",
        "Unicorn": "Unicorn",
        "Does": "Does",
        "SF": "SF",
        "leadership": "leadership",
        "sound": "sound",
        "Rub": "Rub",
        "Java": "Java",
        "building": "building",
        "systems": "systems",
        "team": "team",
        "mid": "mid",
        "engineers": "engineers",
        "Building": "Building",
        "e-commerce": "e-commerce",
        "platformUtilize": "platformUtilize",
        "edge": "edge",
        "technologies": "technologies",
        "Leadership": "Leadership",
        "BSCS": "BSCS",
        "Computer": "Computer",
        "Science": "Science",
        "field": "field",
        "industry": "industry",
        "experienceStrong": "experienceStrong",
        "software": "software",
        "architecture": "architecture",
        "designStrong": "designStrong",
        "python": "python",
        "language": "language",
        "java": "java",
        "C++": "C++",
        "languages": "languages",
        "databases": "databases",
        "Exposure": "Exposure",
        "scale": "scale",
        "environments": "environments",
        "past": "past",
        "websites": "websites",
        "DevOps": "DevOps",
        "Systems": "Systems",
        "tasks": "tasks",
        "PlusesExperience": "PlusesExperience",
        "Kubernetes": "Kubernetes",
        "Docker": "Docker",
        "ContainerizationBenefits": "ContainerizationBenefits",
        "Industry": "Industry",
        "Compensation": "Compensation",
        "PackageStrong": "PackageStrong",
        "benefits": "benefits",
        "package+vacation": "package+vacation",
        "time": "time",
        "day": "day",
        "work": "work",
        "office": "office",
        "environment": "environment",
        "lunches": "lunches",
        "plenty": "plenty",
        "perks": "perks",
        "challenge": "challenge",
        "resume": "resume",
        "harrington": "harrington",
        "collabera": "collabera",
        "DetailsJob": "DetailsJob",
        "Typefulltime": "Typefulltime",
        "days": "days"
      },
      "ADJ": {
        "interested": "interested",
        "next": "next",
        "e-commerce": "e-commerce",
        "profitable": "profitable",
        "verified": "verified",
        "top-tier": "top-tier",
        "well-versed": "well-versed",
        "scalable": "scalable",
        "amazing": "amazing",
        "principal": "principal",
        "functional": "functional",
        "related": "related",
        "equivalent": "equivalent",
        "strong": "strong",
        "Strong": "Strong",
        "relational": "relational",
        "large": "large",
        "in-production": "in-production",
        "stockOne": "stockOne",
        "homeGreat": "homeGreat",
        "other": "other",
        "ready": "ready",
        "comJob": "comJob"
      },
      "VERB": {
        "is": "is",
        "revolutionizing": "revolutionizing",
        "being": "being",
        "building": "building",
        "interesting": "interesting",
        "are": "are",
        "have": "have",
        "read": "read",
        "growing": "growing",
        "looking": "looking",
        "'ll": "'ll",
        "be": "be",
        "working": "working",
        "creating": "creating",
        "cutting": "cutting",
        "build": "build",
        "mentoring": "mentoring",
        "must": "must",
        "scripting": "scripting",
        "compiled": "compiled",
        "Able": "Able",
        "take": "take",
        "Leading": "Leading",
        "catered": "catered",
        "please": "please",
        "send": "send",
        "alexander": "alexander",
        "contractPosted": "contractPosted"
      },
      "PRT": {
        "out": "out",
        "to": "to"
      }
    }
  },
  "217669897": {
    "Company": "Randstad Technologies",
    "Job Title": "Senior Software Test Automation Engineer",
    "Job Details": "Description job summary:Summary\nThe  test automation engineer will develop test infrastructure, test fixtures and implement test scripts for the robotic system|||| He/she will collect and analyze data to verify, validate and measure software product quality and performance throughout the software development lifecycle|||| He/she will be responsible for writing test procedures, test reports, executing test plans and filing bugs|||| The candidate must be comfortable working with complex electro-mechanical systems, deploying new software releases and running test protocols on the systems|||| The candidate will work in close relationship with the software developers to integrate and improve test infrastructure in existing software solutions|||| We are looking for a candidate that can work independently and function well within a team, is self-motivated, detail-oriented, takes testing and automation as his/her true passion and wants bring software to an exceptional level of reliability||||\n location: Redwood City, Californiajob type: Contractsalary: $70 - 80  per hourwork hours: 8am to 4pmeducation: Bachelors responsibilities:Responsibilities\n•Design and develop test automation system and test fixtures•Design and implement sophisticated automated tests for software and hardware\n\tcomponents||||•Improve test automation scripts and coverage||||•Create test protocols and test reports•Implement and execute functional tests, unit tests, stress tests and performance tests||||•Collect, analyze, track and report test results|||| Document and file bugs||||•Participate in design discussions and code reviews||||•Mentoring team on test automationQualifications\nBachelor's in Software (or) Electrical/Electronics Engineering, or related field plus five years of progressive post-graduate experience in software test engineering||||\nSpecial Requirements\n•Deep knowledge of white/gray/black box testing methodologies with hands-on experience||||•strong understanding of test methodologies (such as performance, load, stress, functional, unit,•etc||||)•strong programming skills in Python and C/C++ languages•Understanding of object oriented design, design patterns and multithreaded applications||||•Experience with scripting languages such as Python, Shell, Batch, Bash and Linux commands||||•strong analytical skills, capable of uncovering anomalies in robust software||||•Software testing for complex electro-mechanical systems (Medical device preferred)||||•Knowledge of IEC 62304, ISO 14971, and ISO 13485||||•Experience with automated GUI testing tools such as Squish•Experience with networking tools for troubleshooting issues related to data transfer and•performance across a network||||•Experience with Windows and Linux operating systems•Experience with JIRA or any similar bug tracking tools||||•Experience with JAMA or any similar test management tools|||| qualifications:•Experience level: Experienced•Minimum 4 years of experience•Education: Bachelors skills: •C++•Python•automation testing•testing methodsEqual Opportunity Employer: Race, Color, Religion, Sex, Sexual Orientation, Gender Identity, National Origin, Age, Genetic Information, Disability, Protected Veteran Status, or any other legally protected group status|||| Qualified applicants in San Francisco with criminal histories will be considered for employment in accordance with the San Francisco Fair Chance Ordinance|||| We will consider for employment all qualified Applicants, including those with criminal histories, in a manner consistent with the requirements of applicable state and local laws, including the City of Los Angeles' Fair Chance Initiative for Hiring Ordinance||||\nJob DetailsSalary$70 - $80 Per HourJob Typefulltime, contractPosted 6 days ago||||",
    "KeyWords": {
      "NOUN": {
        "job": "job",
        "summary": "summary",
        "test": "test",
        "automation": "automation",
        "engineer": "engineer",
        "infrastructure": "infrastructure",
        "fixtures": "fixtures",
        "scripts": "scripts",
        "system": "system",
        "He/she": "He/she",
        "data": "data",
        "validate": "validate",
        "measure": "measure",
        "software": "software",
        "product": "product",
        "quality": "quality",
        "performance": "performance",
        "development": "development",
        "lifecycle": "lifecycle",
        "procedures": "procedures",
        "reports": "reports",
        "plans": "plans",
        "bugs": "bugs",
        "candidate": "candidate",
        "systems": "systems",
        "releases": "releases",
        "protocols": "protocols",
        "relationship": "relationship",
        "developers": "developers",
        "solutions": "solutions",
        "function": "function",
        "team": "team",
        "his/her": "his/her",
        "passion": "passion",
        "level": "level",
        "reliability": "reliability",
        "location": "location",
        "Redwood": "Redwood",
        "City": "City",
        "Californiajob": "Californiajob",
        "type": "type",
        "hourwork": "hourwork",
        "hours": "hours",
        "Bachelors": "Bachelors",
        "responsibilities": "responsibilities",
        "Responsibilities": "Responsibilities",
        "fixtures•Design": "fixtures•Design",
        "implement": "implement",
        "tests": "tests",
        "hardware": "hardware",
        "components": "components",
        "coverage": "coverage",
        "reports•Implement": "reports•Implement",
        "unit": "unit",
        "stress": "stress",
        "•Collect": "•Collect",
        "analyze": "analyze",
        "track": "track",
        "report": "report",
        "results": "results",
        "Document": "Document",
        "file": "file",
        "•Participate": "•Participate",
        "design": "design",
        "discussions": "discussions",
        "code": "code",
        "reviews": "reviews",
        "automationQualifications": "automationQualifications",
        "Bachelor": "Bachelor",
        "Software": "Software",
        "Electrical/Electronics": "Electrical/Electronics",
        "Engineering": "Engineering",
        "field": "field",
        "years": "years",
        "experience": "experience",
        "engineering": "engineering",
        "Requirements": "Requirements",
        "knowledge": "knowledge",
        "white/gray/black": "white/gray/black",
        "box": "box",
        "methodologies": "methodologies",
        "understanding": "understanding",
        "load": "load",
        "•etc": "•etc",
        "skills": "skills",
        "Python": "Python",
        "C/C++": "C/C++",
        "languages•Understanding": "languages•Understanding",
        "object": "object",
        "patterns": "patterns",
        "applications": "applications",
        "•Experience": "•Experience",
        "languages": "languages",
        "Shell": "Shell",
        "Batch": "Batch",
        "Bash": "Bash",
        "Linux": "Linux",
        "commands": "commands",
        "anomalies": "anomalies",
        "•Software": "•Software",
        "device": "device",
        "•Knowledge": "•Knowledge",
        "IEC": "IEC",
        "ISO": "ISO",
        "GUI": "GUI",
        "testing": "testing",
        "tools": "tools",
        "Squish•Experience": "Squish•Experience",
        "networking": "networking",
        "issues": "issues",
        "transfer": "transfer",
        "and•performance": "and•performance",
        "network": "network",
        "Windows": "Windows",
        "systems•Experience": "systems•Experience",
        "JIRA": "JIRA",
        "bug": "bug",
        "tracking": "tracking",
        "JAMA": "JAMA",
        "management": "management",
        "qualifications": "qualifications",
        "experience•Education": "experience•Education",
        "•C++•Python•automation": "•C++•Python•automation",
        "Opportunity": "Opportunity",
        "Employer": "Employer",
        "Race": "Race",
        "Color": "Color",
        "Religion": "Religion",
        "Sex": "Sex",
        "Sexual": "Sexual",
        "Orientation": "Orientation",
        "Gender": "Gender",
        "Identity": "Identity",
        "National": "National",
        "Origin": "Origin",
        "Age": "Age",
        "Genetic": "Genetic",
        "Information": "Information",
        "Disability": "Disability",
        "Protected": "Protected",
        "Veteran": "Veteran",
        "Status": "Status",
        "group": "group",
        "status": "status",
        "applicants": "applicants",
        "San": "San",
        "Francisco": "Francisco",
        "histories": "histories",
        "employment": "employment",
        "accordance": "accordance",
        "Fair": "Fair",
        "Chance": "Chance",
        "Ordinance": "Ordinance",
        "Applicants": "Applicants",
        "manner": "manner",
        "requirements": "requirements",
        "state": "state",
        "laws": "laws",
        "Los": "Los",
        "Angeles": "Angeles",
        "Initiative": "Initiative",
        "Job": "Job",
        "DetailsSalary": "DetailsSalary",
        "Per": "Per",
        "HourJob": "HourJob",
        "Typefulltime": "Typefulltime",
        "days": "days"
      },
      "ADJ": {
        "implement": "implement",
        "robotic": "robotic",
        "responsible": "responsible",
        "comfortable": "comfortable",
        "complex": "complex",
        "electro-mechanical": "electro-mechanical",
        "new": "new",
        "close": "close",
        "self-motivated": "self-motivated",
        "detail-oriented": "detail-oriented",
        "true": "true",
        "exceptional": "exceptional",
        "Contractsalary": "Contractsalary",
        "sophisticated": "sophisticated",
        "automated": "automated",
        "•Create": "•Create",
        "execute": "execute",
        "functional": "functional",
        "related": "related",
        "progressive": "progressive",
        "post-graduate": "post-graduate",
        "Special": "Special",
        "•Deep": "•Deep",
        "hands-on": "hands-on",
        "•strong": "•strong",
        "such": "such",
        "analytical": "analytical",
        "capable": "capable",
        "robust": "robust",
        "Medical": "Medical",
        "similar": "similar",
        "Experienced•Minimum": "Experienced•Minimum",
        "methodsEqual": "methodsEqual",
        "other": "other",
        "criminal": "criminal",
        "consistent": "consistent",
        "applicable": "applicable",
        "local": "local"
      },
      "VERB": {
        "develop": "develop",
        "will": "will",
        "collect": "collect",
        "analyze": "analyze",
        "verify": "verify",
        "be": "be",
        "writing": "writing",
        "executing": "executing",
        "filing": "filing",
        "must": "must",
        "working": "working",
        "deploying": "deploying",
        "running": "running",
        "work": "work",
        "integrate": "integrate",
        "improve": "improve",
        "existing": "existing",
        "are": "are",
        "looking": "looking",
        "can": "can",
        "is": "is",
        "takes": "takes",
        "testing": "testing",
        "wants": "wants",
        "bring": "bring",
        "•Design": "•Design",
        "•Improve": "•Improve",
        "•Mentoring": "•Mentoring",
        "programming": "programming",
        "oriented": "oriented",
        "multithreaded": "multithreaded",
        "scripting": "scripting",
        "uncovering": "uncovering",
        "preferred": "preferred",
        "troubleshooting": "troubleshooting",
        "related": "related",
        "operating": "operating",
        "testing•testing": "testing•testing",
        "protected": "protected",
        "Qualified": "Qualified",
        "considered": "considered",
        "consider": "consider",
        "qualified": "qualified",
        "including": "including",
        "Hiring": "Hiring",
        "contractPosted": "contractPosted"
      },
      "PRT": {
        "to": "to",
        "'s": "'s"
      },
      "NUM": {
        "70": "70",
        "80": "80",
        "13485": "13485",
        "14971": "14971",
        "62304": "62304",
        "8am": "8am",
        "4pmeducation": "4pmeducation",
        "five": "five"
      }
    }
  },
  "217689919": {
    "Company": "QualiTest",
    "Job Title": "5766 - Senior Automation Test Engineer (Python)",
    "Job Details": "DescriptionAre you interested in working with the largest independent software testing company? Read on! QualiTest is looking for a Senior Automation Test Engineer in Redwood City, CA||||  Candidates should be able to create test plans, test cases, and test plans from scratch  Responsible for development of a sustainable and maintainable automation framework using Serenity BDD / Selenium|||| Assist in Planning, organizing, monitoring, and oversight of all phases of test automation Responsible for providing key metrics and status updates to the test lead throughout the project Work closely with other project groups to increase the quality of software delivered Highlight requirement and design gaps as early in life cycle as possible  Engage with application development team in defect resolution  Provide training to project core team members covering automation activities as needed  Facilitate test automation meetings, escalating issues/concerns to the project management team, test lead or project manager as needed Implementation of core test Automation strategy and framework|||| Requirements MUST HAVE test automation experience with Selenium/Python|||| MUST HAVE experience with API automation using REST/SOAP|||| Experience working in Agile/Scrum|||| Experience with tools like Postman||||  Experience with conversion tools like Git or SVN|||| Experience with Jenkins for CI/CD|||| Experience mentoring/training junior members of the team|||| Strong interpersonal and communication skills|||| Experience with system integration testing||||  BenefitsWhy QualiTest?  Have continuous access to and work with Senior Testing Specialists and Practice Experts Be a part of a leading testing company, globally recognized as a Visionary by Gartner Magic Quadrant Work with cutting edge technology in a company built by testers for testers, this is what we do! As a global company, we offer unique placement opportunities around the world Our QualiTesters are the reason for our success, we constantly encourage career development and promote from within  Intrigued to find more about us?  Visit our website at www||||qualitestgroup||||com  Check out our Career page: http://qa-jobs||||qualitestgroup||||com/  If you like what you have read, send us your resume and let’s start talking!\nJob DetailsJob TypefulltimePosted 6 days ago||||",
    "KeyWords": {
      "NOUN": {
        "software": "software",
        "company": "company",
        "QualiTest": "QualiTest",
        "Senior": "Senior",
        "Automation": "Automation",
        "Test": "Test",
        "Engineer": "Engineer",
        "Redwood": "Redwood",
        "City": "City",
        "CA": "CA",
        "Candidates": "Candidates",
        "test": "test",
        "plans": "plans",
        "cases": "cases",
        "scratch": "scratch",
        "Responsible": "Responsible",
        "development": "development",
        "automation": "automation",
        "framework": "framework",
        "Serenity": "Serenity",
        "BDD": "BDD",
        "Selenium": "Selenium",
        "Assist": "Assist",
        "Planning": "Planning",
        "monitoring": "monitoring",
        "oversight": "oversight",
        "phases": "phases",
        "metrics": "metrics",
        "status": "status",
        "updates": "updates",
        "lead": "lead",
        "project": "project",
        "Work": "Work",
        "groups": "groups",
        "quality": "quality",
        "Highlight": "Highlight",
        "requirement": "requirement",
        "design": "design",
        "gaps": "gaps",
        "life": "life",
        "cycle": "cycle",
        "Engage": "Engage",
        "application": "application",
        "team": "team",
        "resolution": "resolution",
        "Provide": "Provide",
        "training": "training",
        "core": "core",
        "members": "members",
        "activities": "activities",
        "Facilitate": "Facilitate",
        "meetings": "meetings",
        "issues/concerns": "issues/concerns",
        "management": "management",
        "manager": "manager",
        "Implementation": "Implementation",
        "strategy": "strategy",
        "Requirements": "Requirements",
        "MUST": "MUST",
        "HAVE": "HAVE",
        "experience": "experience",
        "Selenium/Python": "Selenium/Python",
        "API": "API",
        "REST/SOAP": "REST/SOAP",
        "Experience": "Experience",
        "Agile/Scrum": "Agile/Scrum",
        "tools": "tools",
        "Postman": "Postman",
        "conversion": "conversion",
        "Git": "Git",
        "SVN": "SVN",
        "Jenkins": "Jenkins",
        "CI/CD": "CI/CD",
        "communication": "communication",
        "skills": "skills",
        "system": "system",
        "integration": "integration",
        "BenefitsWhy": "BenefitsWhy",
        "access": "access",
        "work": "work",
        "Testing": "Testing",
        "Specialists": "Specialists",
        "Practice": "Practice",
        "Experts": "Experts",
        "Be": "Be",
        "part": "part",
        "Visionary": "Visionary",
        "Gartner": "Gartner",
        "Magic": "Magic",
        "Quadrant": "Quadrant",
        "edge": "edge",
        "technology": "technology",
        "testers": "testers",
        "placement": "placement",
        "opportunities": "opportunities",
        "world": "world",
        "QualiTesters": "QualiTesters",
        "reason": "reason",
        "success": "success",
        "career": "career",
        "promote": "promote",
        "Intrigued": "Intrigued",
        "website": "website",
        "www": "www",
        "qualitestgroup": "qualitestgroup",
        "Check": "Check",
        "Career": "Career",
        "page": "page",
        "http": "http",
        "resume": "resume",
        "start": "start",
        "Job": "Job",
        "DetailsJob": "DetailsJob",
        "days": "days"
      },
      "ADJ": {
        "largest": "largest",
        "independent": "independent",
        "able": "able",
        "sustainable": "sustainable",
        "maintainable": "maintainable",
        "key": "key",
        "other": "other",
        "possible": "possible",
        "defect": "defect",
        "needed": "needed",
        "junior": "junior",
        "Strong": "Strong",
        "interpersonal": "interpersonal",
        "continuous": "continuous",
        "global": "global",
        "unique": "unique",
        "//qa-jobs": "//qa-jobs"
      },
      "VERB": {
        "testing": "testing",
        "Read": "Read",
        "is": "is",
        "looking": "looking",
        "should": "should",
        "be": "be",
        "create": "create",
        "using": "using",
        "organizing": "organizing",
        "providing": "providing",
        "increase": "increase",
        "delivered": "delivered",
        "project": "project",
        "covering": "covering",
        "escalating": "escalating",
        "needed": "needed",
        "working": "working",
        "mentoring/training": "mentoring/training",
        "Have": "Have",
        "leading": "leading",
        "recognized": "recognized",
        "cutting": "cutting",
        "built": "built",
        "do": "do",
        "offer": "offer",
        "are": "are",
        "encourage": "encourage",
        "find": "find",
        "Visit": "Visit",
        "com": "com",
        "com/": "com/",
        "like": "like",
        "have": "have",
        "read": "read",
        "send": "send",
        "let": "let",
        "talking": "talking",
        "TypefulltimePosted": "TypefulltimePosted"
      },
      "PRT": {
        "to": "to"
      }
    }
  },
  "217702254": {
    "Company": "CyberCoders",
    "Job Title": "Fullstack Software Engineer-ML,Python",
    "Job Details": "DescriptionIf you are a Fullstack Software Engineer-ML,Python with experience, please read on!Top Reasons to Work with UsWe are a computer vision platform that brings transparency to TV providing instant verified analytics||||Work for a front runner in developing industry best computer vision technologies!What You Will Be DoingYou will be joining a team that consists of experienced Ph||||D|||| scientists with specializations in AI, deep learning and computer vision technologies with proven records delivering large government and private sector projects||||What You Need for this PositionMachine LearningAIPythonTensorflowPytorchExperience with API'sTS OR TS-SCI Clearance activeSo, if you are a Fullstack Software Engineer-ML,Python with experience, please apply today!Security Clearance will be needed - therefore, only US citizens can be considered||||Job DetailsJob Typefulltime, employeePosted 5 days ago||||",
    "KeyWords": {
      "NOUN": {
        "Fullstack": "Fullstack",
        "Software": "Software",
        "Engineer-ML": "Engineer-ML",
        "Python": "Python",
        "experience": "experience",
        "please": "please",
        "Reasons": "Reasons",
        "UsWe": "UsWe",
        "computer": "computer",
        "vision": "vision",
        "platform": "platform",
        "transparency": "transparency",
        "TV": "TV",
        "analytics": "analytics",
        "Work": "Work",
        "runner": "runner",
        "industry": "industry",
        "technologies": "technologies",
        "DoingYou": "DoingYou",
        "team": "team",
        "Ph": "Ph",
        "D.": "D.",
        "scientists": "scientists",
        "specializations": "specializations",
        "AI": "AI",
        "learning": "learning",
        "proven": "proven",
        "records": "records",
        "government": "government",
        "sector": "sector",
        "projects": "projects",
        "PositionMachine": "PositionMachine",
        "LearningAIPythonTensorflowPytorchExperience": "LearningAIPythonTensorflowPytorchExperience",
        "API'sTS": "API'sTS",
        "OR": "OR",
        "TS-SCI": "TS-SCI",
        "Clearance": "Clearance",
        "activeSo": "activeSo",
        "today": "today",
        "Security": "Security",
        "therefore": "therefore",
        "citizens": "citizens",
        "Job": "Job",
        "DetailsJob": "DetailsJob",
        "Typefulltime": "Typefulltime",
        "days": "days"
      },
      "VERB": {
        "read": "read",
        "Work": "Work",
        "are": "are",
        "brings": "brings",
        "providing": "providing",
        "developing": "developing",
        "Will": "Will",
        "Be": "Be",
        "will": "will",
        "be": "be",
        "joining": "joining",
        "consists": "consists",
        "delivering": "delivering",
        "Need": "Need",
        "please": "please",
        "apply": "apply",
        "needed": "needed",
        "can": "can",
        "considered": "considered",
        "employeePosted": "employeePosted"
      },
      "ADJ": {
        "instant": "instant",
        "verified": "verified",
        "front": "front",
        "best": "best",
        "experienced": "experienced",
        "deep": "deep",
        "large": "large",
        "private": "private"
      },
      "PRT": {
        "to": "to"
      }
    }
  },
  "217706669": {
    "Company": "Collabera",
    "Job Title": "Software Developer",
    "Job Details": "DescriptionSan Francisco, CaliforniaSkills : Python,Django,Scala,Node||||JS,Node,AWS,Software Developer,Software Development,Software Engineer,Computer Science,Jenkins,Ansible,Kafka,GraphQL,Backend Engineer,Backend Developer,React||||JS,ReduxDescription : We're recruiting for a Software Company based out in Downtown San Francisco, CA|||| They have an immediate opening for a Backend Developer in SF|||| This is a permanent role working for a company that has a great reputation for technically challenging projects|||| If you're an influencer, please read on!Must Haves:-Bachelor's/Master's Degree in Computer Science-3-5 years of experience with Python, Django, Scala-2+ years of experience with Node||||JS, React||||JS, and Redux-Familiarity with some of:-AWS, MySQL, Aerospike, Druid, Redis, Kafka-Experience with continuous deployment systems with tools such as Jenkins or Ansible-Experience with Symphony and Ad Tech-Understanding of common design patternsBenefits:-Competitive base salary ($150K Base) + Equity-Strong benefits package + vacation time-Great office environmentIf you're interested in above opportunity, please send your updated resume on Abhijeetsingh||||sidhu@collabera||||com Job DetailsJob Typefulltime, contractPosted 5 days ago||||",
    "KeyWords": {
      "NOUN": {
        "Francisco": "Francisco",
        "CaliforniaSkills": "CaliforniaSkills",
        "Python": "Python",
        "Django": "Django",
        "Scala": "Scala",
        "Node": "Node",
        "JS": "JS",
        "AWS": "AWS",
        "Software": "Software",
        "Developer": "Developer",
        "Development": "Development",
        "Engineer": "Engineer",
        "Computer": "Computer",
        "Science": "Science",
        "Jenkins": "Jenkins",
        "Ansible": "Ansible",
        "Kafka": "Kafka",
        "GraphQL": "GraphQL",
        "Backend": "Backend",
        "React": "React",
        "ReduxDescription": "ReduxDescription",
        "Company": "Company",
        "Downtown": "Downtown",
        "San": "San",
        "CA": "CA",
        "opening": "opening",
        "SF": "SF",
        "role": "role",
        "company": "company",
        "reputation": "reputation",
        "projects": "projects",
        "influencer": "influencer",
        "Must": "Must",
        "-Bachelor's/Master": "-Bachelor's/Master",
        "Degree": "Degree",
        "Science-3-5": "Science-3-5",
        "years": "years",
        "experience": "experience",
        "Scala-2+": "Scala-2+",
        "Redux-Familiarity": "Redux-Familiarity",
        "-AWS": "-AWS",
        "MySQL": "MySQL",
        "Aerospike": "Aerospike",
        "Druid": "Druid",
        "Redis": "Redis",
        "Kafka-Experience": "Kafka-Experience",
        "systems": "systems",
        "tools": "tools",
        "Ansible-Experience": "Ansible-Experience",
        "Symphony": "Symphony",
        "Ad": "Ad",
        "Tech-Understanding": "Tech-Understanding",
        "design": "design",
        "patternsBenefits": "patternsBenefits",
        "base": "base",
        "salary": "salary",
        "Base": "Base",
        "benefits": "benefits",
        "package": "package",
        "vacation": "vacation",
        "time-Great": "time-Great",
        "office": "office",
        "environmentIf": "environmentIf",
        "opportunity": "opportunity",
        "resume": "resume",
        "Abhijeetsingh": "Abhijeetsingh",
        "sidhu": "sidhu",
        "collabera": "collabera",
        "Job": "Job",
        "DetailsJob": "DetailsJob",
        "Typefulltime": "Typefulltime",
        "days": "days"
      },
      "VERB": {
        "recruiting": "recruiting",
        "based": "based",
        "have": "have",
        "is": "is",
        "working": "working",
        "has": "has",
        "'re": "'re",
        "please": "please",
        "read": "read",
        "Haves": "Haves",
        "send": "send",
        "contractPosted": "contractPosted"
      },
      "PRT": {
        "'s": "'s"
      },
      "ADJ": {
        "permanent": "permanent",
        "great": "great",
        "challenging": "challenging",
        "continuous": "continuous",
        "deployment": "deployment",
        "such": "such",
        "common": "common",
        "-Competitive": "-Competitive",
        "Equity-Strong": "Equity-Strong",
        "interested": "interested",
        "above": "above",
        "updated": "updated",
        "com": "com"
      },
      "NUM": {}
    }
  },
  "217710297": {
    "Company": "NCS Pearson, Inc.",
    "Job Title": "MANAGER SOFTWARE DEVELOPMENT",
    "Job Details": "DescriptionMANAGER SOFTWARE DEVELOPMENTCompany: NCS Pearson, Inc||||Location: San Francisco, CAPosition Type: NAExperience: See below for detailsEducation: See below for detailsManager Software Development sought by NCS Pearson, Inc||||, in SF, CA|||| 40 hrs||||/wk|||| Lead dtaild s/w architecture, dsgn, dlvry & deployment of core s/w pltfrms in content creation & content distr area|||| Act as guide/mentor to all dlvry teams & drive s/w architecture & s/w dsgn across dlvry workstreams|||| Respsbl for creating most optimal s/w dsgn that can scale & prfrm in a direct to consumer envrmnt|||| Directly involved in prblm solving & res of day-to-day dsgn issues; translate the high-level architecture to s/w dsgn that dlvry teams can code to; & play a key role in defining high-level architecture, working closely w/ Enterprise Architecture team|||| Will be the bridge btwn Enterprise Architecture & Dlvry & also act as the bridge btwn Dlvry & Ops, working closely w/ Ops team to dvlp system dsgn for public cloud deployment & drive cutting edge cloud tech adoption within dlvry teams|||| Reqs: Bachelor’s in CS, Computer Info Sys, Engg, or a rltd field, or frgn equiv, or equiv; & 5 yrs’ exp as Sr|||| S/w Engineer, Tech Director, Assoc Tech Architect, or rltd pos, w/ strg fundamentals (such as data structures, computational algorithms, & operating sys||||) & 5 yrs of s/w engg exp bldg scalable, high-quality sys in a direct-to-consumer biz|||| 5 yrs’ exp working w/ open source pltfrms, API dvlpmt , REST/SOAP, Linux, Java, Javascript, C#, python, Go, C++, SQL/MongoDB/NoSQL d/b's|||| Exp leading platform dvlpmt using micro-services in AWS|||| 5 yrs’ exp leading small to medium sized s/w engg teams in an Agile/SCRUM envrmnt|||| 5 yrs of hands-on exp as fullstack dvlpr, at all tiers from the front end UI to the backend data store|||| Must possess rcrd of dvlpng high qlty s/w prdcts & shipping prod ready s/w on sched|||| Reply with resume to: Joseph Ciccia, NCS Pearson, Inc||||, 221 River St, Hoboken, NJ 07030; or Joseph||||Ciccia@pearson||||com||||Job DetailsJob Typefulltime, employeePosted 2 days ago||||",
    "KeyWords": {
      "NOUN": {
        "SOFTWARE": "SOFTWARE",
        "DEVELOPMENTCompany": "DEVELOPMENTCompany",
        "NCS": "NCS",
        "Pearson": "Pearson",
        "Inc": "Inc",
        "Location": "Location",
        "San": "San",
        "Francisco": "Francisco",
        "CAPosition": "CAPosition",
        "Type": "Type",
        "NAExperience": "NAExperience",
        "detailsEducation": "detailsEducation",
        "detailsManager": "detailsManager",
        "Software": "Software",
        "Development": "Development",
        "Inc.": "Inc.",
        "SF": "SF",
        "CA": "CA",
        "hrs": "hrs",
        "/wk": "/wk",
        "architecture": "architecture",
        "dsgn": "dsgn",
        "dlvry": "dlvry",
        "deployment": "deployment",
        "core": "core",
        "s/w": "s/w",
        "pltfrms": "pltfrms",
        "creation": "creation",
        "content": "content",
        "distr": "distr",
        "area": "area",
        "Act": "Act",
        "guide/mentor": "guide/mentor",
        "teams": "teams",
        "drive": "drive",
        "workstreams": "workstreams",
        "Respsbl": "Respsbl",
        "consumer": "consumer",
        "envrmnt": "envrmnt",
        "prblm": "prblm",
        "res": "res",
        "issues": "issues",
        "role": "role",
        "Enterprise": "Enterprise",
        "Architecture": "Architecture",
        "team": "team",
        "bridge": "bridge",
        "btwn": "btwn",
        "Dlvry": "Dlvry",
        "act": "act",
        "Ops": "Ops",
        "system": "system",
        "cloud": "cloud",
        "cutting": "cutting",
        "edge": "edge",
        "tech": "tech",
        "adoption": "adoption",
        "Reqs": "Reqs",
        "Bachelor": "Bachelor",
        "CS": "CS",
        "Computer": "Computer",
        "Info": "Info",
        "Sys": "Sys",
        "Engg": "Engg",
        "field": "field",
        "equiv": "equiv",
        "yrs": "yrs",
        "exp": "exp",
        "Sr.": "Sr.",
        "S/w": "S/w",
        "Engineer": "Engineer",
        "Tech": "Tech",
        "Director": "Director",
        "Assoc": "Assoc",
        "Architect": "Architect",
        "pos": "pos",
        "fundamentals": "fundamentals",
        "data": "data",
        "structures": "structures",
        "algorithms": "algorithms",
        "sys": "sys",
        "engg": "engg",
        "bldg": "bldg",
        "biz": "biz",
        "w/": "w/",
        "source": "source",
        "API": "API",
        "dvlpmt": "dvlpmt",
        "REST/SOAP": "REST/SOAP",
        "Linux": "Linux",
        "Java": "Java",
        "Javascript": "Javascript",
        "python": "python",
        "Go": "Go",
        "C++": "C++",
        "SQL/MongoDB/NoSQL": "SQL/MongoDB/NoSQL",
        "d/b": "d/b",
        "Exp": "Exp",
        "platform": "platform",
        "micro-services": "micro-services",
        "AWS": "AWS",
        "Agile/SCRUM": "Agile/SCRUM",
        "fullstack": "fullstack",
        "dvlpr": "dvlpr",
        "tiers": "tiers",
        "end": "end",
        "UI": "UI",
        "backend": "backend",
        "store": "store",
        "Must": "Must",
        "rcrd": "rcrd",
        "qlty": "qlty",
        "prod": "prod",
        "resume": "resume",
        "Joseph": "Joseph",
        "Ciccia": "Ciccia",
        "River": "River",
        "St": "St",
        "Hoboken": "Hoboken",
        "NJ": "NJ",
        "pearson": "pearson",
        "com": "com",
        "Job": "Job",
        "DetailsJob": "DetailsJob",
        "Typefulltime": "Typefulltime",
        "days": "days"
      },
      "VERB": {
        "See": "See",
        "sought": "sought",
        "creating": "creating",
        "can": "can",
        "scale": "scale",
        "prfrm": "prfrm",
        "involved": "involved",
        "solving": "solving",
        "translate": "translate",
        "s/w": "s/w",
        "code": "code",
        "play": "play",
        "defining": "defining",
        "working": "working",
        "Will": "Will",
        "be": "be",
        "dvlp": "dvlp",
        "rltd": "rltd",
        "operating": "operating",
        "leading": "leading",
        "using": "using",
        "medium": "medium",
        "prdcts": "prdcts",
        "shipping": "shipping",
        "sched": "sched",
        "Reply": "Reply",
        "employeePosted": "employeePosted"
      },
      "NUM": {
        "221": "221",
        "07030": "07030"
      },
      "ADJ": {
        "dtaild": "dtaild",
        "s/w": "s/w",
        "content": "content",
        "dlvry": "dlvry",
        "most": "most",
        "optimal": "optimal",
        "direct": "direct",
        "day-to-day": "day-to-day",
        "high-level": "high-level",
        "key": "key",
        "w/": "w/",
        "public": "public",
        "rltd": "rltd",
        "frgn": "frgn",
        "strg": "strg",
        "such": "such",
        "computational": "computational",
        "scalable": "scalable",
        "high-quality": "high-quality",
        "direct-to-consumer": "direct-to-consumer",
        "yrs": "yrs",
        "open": "open",
        "small": "small",
        "sized": "sized",
        "hands-on": "hands-on",
        "front": "front",
        "possess": "possess",
        "dvlpng": "dvlpng",
        "high": "high",
        "ready": "ready"
      },
      "PRT": {
        "to": "to",
        "'s": "'s"
      }
    }
  },
  "217719873": {
    "Company": "CyberCoders",
    "Job Title": "Sr. Genomics Data Engineer  - Spark, Python, AI",
    "Job Details": "DescriptionIf you are a Sr|||| Data Engineer with a background in Human Genomics and strong Apache Spark experience, please read on!\nHeadquartered out of beautiful Oakland, we are a cutting-edge AI-Driven Genomics Biotech company! Established in 2011, we analyze and interpret complex genomic data from raw data to variant cells, from whole genome, exome, or panel tests to increase diagnostic yield|||| We are trailblazers, tenaciously deciphering human biology when it comes to hereditary disease and oncology|||| Our platform substantially reduces genome interpretation time in the diagnosis of monogenic diseases, which allows cost-effective, automated reanalysis of undiagnosed cases||||\n\nIf you have a passion for the complex and beautiful combination of Data and Genomics with a strong background in Apache Spark, we would love to hear from you!Top Reasons to Work with Us1|||| Fast-Growing AI-Driven Genomics Company!2|||| Opportunity for Professional Growth!\n3|||| Competitive Base Salary, Benefits, and Great Company Culture!What You Will Be Doing- Build out a big data distributed architecture capable of efficiently processing large-scale genomics data||||- Develop / deploy bioinformatics and AI analysis algorithms at scale||||\n- Build automated production-quality data processing systems||||\n- Interact and collaborate with scientists to clearly define / iterate on requirements||||\n- Keep abreast of new software data engineering and data science technologies||||\n- Aggregate / analyze genomic and other types of clinical data to find novel insights||||\n- Develop code to implement analysis workflows in a robust and reproducible fashion||||\n- Follow processes to improve transparency and reliability of applications, reducing project risks for on-time milestones||||\n- Educate other scientists, engineers, and management on the methods developed and how they apply to the subject domain and customer needs||||What You Need for this Position- Bachelor's Degree in Computer Science, Technology, or related|||| - 2+ years of experience working with Genomics Data||||\n- Must have experience with cluster-computing framework Apache Spark|||| \n- Programming/scripting experience with Python||||\n\nBonus Points:\n- Background using Scala||||\n- Proficiency with SQL database and scripting||||\n- Experience with Amazon Web Services (AWS)||||What's In It for YouFor your hard work and dedication, you will be rewarded with a competitive base salary, and excellent benefits including but not limited to:- Salary ($150k - $180k DOE)\n- Vacation/PTO \n- Medical\n- Dental\n- Vision\n- Bonus (10%)\n- 401k\n- EquitySo, if you are a Sr|||| Genomics Data Engineer with Apache Spark experience, please apply today!Job DetailsSalary$150000 - $200000 Per YearJob Typefulltime, employeePosted 6 days ago||||",
    "KeyWords": {
      "NOUN": {
        "Sr.": "Sr.",
        "Data": "Data",
        "Engineer": "Engineer",
        "background": "background",
        "Human": "Human",
        "Genomics": "Genomics",
        "Apache": "Apache",
        "Spark": "Spark",
        "experience": "experience",
        "please": "please",
        "Oakland": "Oakland",
        "Biotech": "Biotech",
        "company": "company",
        "data": "data",
        "cells": "cells",
        "genome": "genome",
        "exome": "exome",
        "panel": "panel",
        "tests": "tests",
        "yield": "yield",
        "trailblazers": "trailblazers",
        "biology": "biology",
        "disease": "disease",
        "oncology": "oncology",
        "platform": "platform",
        "interpretation": "interpretation",
        "time": "time",
        "diagnosis": "diagnosis",
        "diseases": "diseases",
        "cost-effective": "cost-effective",
        "reanalysis": "reanalysis",
        "cases": "cases",
        "passion": "passion",
        "combination": "combination",
        "Reasons": "Reasons",
        "Us1": "Us1",
        "Company": "Company",
        "Opportunity": "Opportunity",
        "Professional": "Professional",
        "Growth": "Growth",
        "Base": "Base",
        "Salary": "Salary",
        "Benefits": "Benefits",
        "Great": "Great",
        "Culture": "Culture",
        "Doing-": "Doing-",
        "Build": "Build",
        "architecture": "architecture",
        "genomics": "genomics",
        "Develop": "Develop",
        "deploy": "deploy",
        "bioinformatics": "bioinformatics",
        "AI": "AI",
        "analysis": "analysis",
        "algorithms": "algorithms",
        "scale": "scale",
        "production-quality": "production-quality",
        "systems": "systems",
        "Interact": "Interact",
        "collaborate": "collaborate",
        "scientists": "scientists",
        "iterate": "iterate",
        "requirements": "requirements",
        "Keep": "Keep",
        "abreast": "abreast",
        "software": "software",
        "engineering": "engineering",
        "science": "science",
        "technologies": "technologies",
        "Aggregate": "Aggregate",
        "types": "types",
        "insights": "insights",
        "code": "code",
        "workflows": "workflows",
        "fashion": "fashion",
        "processes": "processes",
        "transparency": "transparency",
        "reliability": "reliability",
        "applications": "applications",
        "project": "project",
        "risks": "risks",
        "milestones": "milestones",
        "Educate": "Educate",
        "engineers": "engineers",
        "management": "management",
        "methods": "methods",
        "subject": "subject",
        "domain": "domain",
        "customer": "customer",
        "needs": "needs",
        "Position-": "Position-",
        "Bachelor": "Bachelor",
        "Degree": "Degree",
        "Computer": "Computer",
        "Science": "Science",
        "Technology": "Technology",
        "years": "years",
        "Must": "Must",
        "framework": "framework",
        "Python": "Python",
        "Bonus": "Bonus",
        "Points": "Points",
        "Scala": "Scala",
        "Proficiency": "Proficiency",
        "SQL": "SQL",
        "database": "database",
        "scripting": "scripting",
        "Experience": "Experience",
        "Amazon": "Amazon",
        "Web": "Web",
        "Services": "Services",
        "AWS": "AWS",
        "YouFor": "YouFor",
        "work": "work",
        "dedication": "dedication",
        "base": "base",
        "salary": "salary",
        "benefits": "benefits",
        "DOE": "DOE",
        "Vision": "Vision",
        "EquitySo": "EquitySo",
        "today": "today",
        "Job": "Job",
        "DetailsSalary": "DetailsSalary",
        "Per": "Per",
        "YearJob": "YearJob",
        "Typefulltime": "Typefulltime",
        "days": "days"
      },
      "VERB": {
        "read": "read",
        "Headquartered": "Headquartered",
        "are": "are",
        "Established": "Established",
        "analyze": "analyze",
        "interpret": "interpret",
        "variant": "variant",
        "increase": "increase",
        "deciphering": "deciphering",
        "comes": "comes",
        "reduces": "reduces",
        "allows": "allows",
        "automated": "automated",
        "have": "have",
        "would": "would",
        "love": "love",
        "hear": "hear",
        "Work": "Work",
        "Will": "Will",
        "Be": "Be",
        "distributed": "distributed",
        "processing": "processing",
        "define": "define",
        "find": "find",
        "Develop": "Develop",
        "implement": "implement",
        "improve": "improve",
        "reducing": "reducing",
        "developed": "developed",
        "apply": "apply",
        "Need": "Need",
        "related": "related",
        "working": "working",
        "Programming/scripting": "Programming/scripting",
        "using": "using",
        "'s": "'s",
        "will": "will",
        "be": "be",
        "rewarded": "rewarded",
        "including": "including",
        "please": "please",
        "employeePosted": "employeePosted"
      },
      "ADJ": {
        "beautiful": "beautiful",
        "cutting-edge": "cutting-edge",
        "AI-Driven": "AI-Driven",
        "complex": "complex",
        "genomic": "genomic",
        "raw": "raw",
        "whole": "whole",
        "diagnostic": "diagnostic",
        "human": "human",
        "hereditary": "hereditary",
        "genome": "genome",
        "monogenic": "monogenic",
        "undiagnosed": "undiagnosed",
        "strong": "strong",
        "Top": "Top",
        "Fast-Growing": "Fast-Growing",
        "Competitive": "Competitive",
        "big": "big",
        "capable": "capable",
        "large-scale": "large-scale",
        "new": "new",
        "other": "other",
        "clinical": "clinical",
        "novel": "novel",
        "robust": "robust",
        "reproducible": "reproducible",
        "Follow": "Follow",
        "on-time": "on-time",
        "cluster-computing": "cluster-computing",
        "hard": "hard",
        "competitive": "competitive",
        "excellent": "excellent",
        "limited": "limited",
        "Medical": "Medical",
        "Dental": "Dental"
      },
      "NUM": {
        "10": "10",
        "150000": "150000",
        "200000": "200000",
        "2+": "2+",
        "150k": "150k",
        "180k": "180k",
        "401k": "401k"
      },
      "PRT": {
        "to": "to",
        "out": "out",
        "'s": "'s"
      },
      "X": {}
    }
  },
  "217732835": {
    "Company": "Smart IMS",
    "Job Title": "Sr. Data Engineer - data warehousing",
    "Job Details": "Description Required Skill Set: Automation, CI/CD tools, Java, JSON, Production Support, Python, Scala, Spring Framework, SQL, XML Job Description:Identify and resolve performance bottlenecks either proactivelyWork with the customer support group as needed to resolve performance issues in the fieldExplore automation opportunity and develop tools to automate some of the day to day operations tasksProvide performance metrics and maintain dashboards to reflect production systems healthConceptualize and implement proactive monitoring where possible to catch issues earlyExperiment with new tools to streamline the development, testing, deployment, and running of our data pipelines||||Work with cross functional agile teams to drive projects through full development cycle||||Help the team improve with the usage of data engineering best practices||||Collaborate with other data engineering teams to improve the data engineering ecosystem and talentCreatively solve problems when facing constraints, whether it is the number of developers, quality or quantity of data, compute power, storage capacity or just time||||Maintain awareness of relevant technical and product trends through self-learning/study, training classes and job shadowing||||Role Partner on the design the next implementation of Client secure, global data and insight architecture, building new Stream processing capabilities and operationalizing \"Unified Data Acquisition and Processing (UDAP) platform\" Own medium-to-large size data engineering projects Discover, ingest, and incorporate new sources of real-time, streaming, batch, and API-based data into our platform to enhance the insights we get from running tests and expand the ways and properties on which we can test Assist business in utilizing data-driven insights to drive growth and transformation|||| Build and maintain data processing workflows feeding client analytics domains|||| Facilitate reliable integrations with internal systems and third-party API''s as needed|||| Support data analysts as needed, advising on data definitions and helping them derive meaning from complex datasets|||| Prototype new algorithms, experiment, evaluate and deliver actionable insights|||| Experiment with new tools to streamline the development, testing, deployment, and running of our data pipelines|||| Work with cross functional agile teams to drive projects through full development cycle|||| Help the team improve with the usage of data engineering best practices|||| Collaborate with other data engineering teams to improve the data engineering ecosystem and talent within Client|||| Creatively solve problems when facing constraints, whether it is the number of developers, quality or quantity of data, compute power, storage capacity or just time|||| Maintain awareness of relevant technical and product trends through self-learning/study, training classes and job shadowing|||| All About You At least Bachelor''s degree in Computer Science, Computer Engineering or Technology related field or equivalent work experience5 to 10 years of experience in Data Warehouse related projects in product or service based organizationExpertise in Data Engineering and implementing multiple end-to-end DW projects in Big Data environmentExperience in building and deploying production level data driven applications and data processing workflows/pipelines Experience with application development frameworks (Java/Scala, Spring) Experience with data processing and storage frameworks like Hadoop, Spark, Kafka Experience implementing REST services with support for JSON, XML and other formats Experience with performance Tuning of Database Schemas, Databases, SQL, ETL Jobs, and related scripts Experience of working in Agile teamsStrong analytical skills required for debugging production issues, providing root cause and implementing mitigation plan Strong communication skills - both verbal and written - and strong relationship, collaboration skills and organizational skillsAbility to be high-energy, detail-oriented, proactive and able to function under pressure in an independent environment along with a high degree of initiative and self-motivation to drive resultsAbility to quickly learn and implement new technologies, and perform POC to explore best solution for the problem statement Flexibility to work as a member of a matrix based diverse and geographically distributed project teams Nice To Have:Strong familiarity with batch processing and workflow tools such as NiFiFamiliarity with modern BI and data exploration tools||||Experience in developing integrated cloud applications with services like Azure or GCPExperience implementing machine learning systems at scale in Java, Scala, or Python and deliver analytics involving all phases like data ingestion, feature engineering, modeling, tuning, evaluating, monitoring and presenting REQUIREMENTS:At least 3 years of experience Java/Scala/Python Development Spring framework Spark , Big Data technologies such as Hadoop , Hive Job DetailsJob Typefulltime, employeePosted 3 days ago||||",
    "KeyWords": {
      "NOUN": {
        "Required": "Required",
        "Skill": "Skill",
        "Set": "Set",
        "Automation": "Automation",
        "CI/CD": "CI/CD",
        "Java": "Java",
        "JSON": "JSON",
        "Production": "Production",
        "Support": "Support",
        "Python": "Python",
        "Scala": "Scala",
        "Spring": "Spring",
        "Framework": "Framework",
        "SQL": "SQL",
        "XML": "XML",
        "Job": "Job",
        "Description": "Description",
        "Identify": "Identify",
        "performance": "performance",
        "bottlenecks": "bottlenecks",
        "proactivelyWork": "proactivelyWork",
        "customer": "customer",
        "support": "support",
        "group": "group",
        "issues": "issues",
        "fieldExplore": "fieldExplore",
        "automation": "automation",
        "opportunity": "opportunity",
        "tools": "tools",
        "day": "day",
        "operations": "operations",
        "metrics": "metrics",
        "maintain": "maintain",
        "dashboards": "dashboards",
        "production": "production",
        "systems": "systems",
        "healthConceptualize": "healthConceptualize",
        "proactive": "proactive",
        "monitoring": "monitoring",
        "development": "development",
        "deployment": "deployment",
        "running": "running",
        "data": "data",
        "pipelines": "pipelines",
        "Work": "Work",
        "agile": "agile",
        "teams": "teams",
        "projects": "projects",
        "cycle": "cycle",
        "team": "team",
        "usage": "usage",
        "engineering": "engineering",
        "practices": "practices",
        "Collaborate": "Collaborate",
        "ecosystem": "ecosystem",
        "problems": "problems",
        "constraints": "constraints",
        "number": "number",
        "developers": "developers",
        "quality": "quality",
        "quantity": "quantity",
        "compute": "compute",
        "power": "power",
        "storage": "storage",
        "capacity": "capacity",
        "time": "time",
        "Maintain": "Maintain",
        "awareness": "awareness",
        "product": "product",
        "trends": "trends",
        "self-learning/study": "self-learning/study",
        "training": "training",
        "classes": "classes",
        "job": "job",
        "Role": "Role",
        "Partner": "Partner",
        "design": "design",
        "implementation": "implementation",
        "Client": "Client",
        "secure": "secure",
        "architecture": "architecture",
        "Stream": "Stream",
        "processing": "processing",
        "capabilities": "capabilities",
        "Data": "Data",
        "Acquisition": "Acquisition",
        "Processing": "Processing",
        "UDAP": "UDAP",
        "platform": "platform",
        "medium-to-large": "medium-to-large",
        "size": "size",
        "Discover": "Discover",
        "ingest": "ingest",
        "sources": "sources",
        "real-time": "real-time",
        "batch": "batch",
        "insights": "insights",
        "tests": "tests",
        "ways": "ways",
        "properties": "properties",
        "Assist": "Assist",
        "business": "business",
        "growth": "growth",
        "transformation": "transformation",
        "Build": "Build",
        "workflows": "workflows",
        "client": "client",
        "analytics": "analytics",
        "domains": "domains",
        "Facilitate": "Facilitate",
        "integrations": "integrations",
        "API": "API",
        "analysts": "analysts",
        "definitions": "definitions",
        "meaning": "meaning",
        "datasets": "datasets",
        "Prototype": "Prototype",
        "algorithms": "algorithms",
        "experiment": "experiment",
        "evaluate": "evaluate",
        "Experiment": "Experiment",
        "talent": "talent",
        "Creatively": "Creatively",
        "shadowing": "shadowing",
        "Bachelor": "Bachelor",
        "degree": "degree",
        "Computer": "Computer",
        "Science": "Science",
        "Engineering": "Engineering",
        "Technology": "Technology",
        "field": "field",
        "work": "work",
        "experience5": "experience5",
        "years": "years",
        "experience": "experience",
        "Warehouse": "Warehouse",
        "service": "service",
        "organizationExpertise": "organizationExpertise",
        "DW": "DW",
        "Big": "Big",
        "environmentExperience": "environmentExperience",
        "building": "building",
        "level": "level",
        "applications": "applications",
        "workflows/pipelines": "workflows/pipelines",
        "Experience": "Experience",
        "application": "application",
        "frameworks": "frameworks",
        "Java/Scala": "Java/Scala",
        "Hadoop": "Hadoop",
        "Spark": "Spark",
        "Kafka": "Kafka",
        "REST": "REST",
        "services": "services",
        "formats": "formats",
        "Tuning": "Tuning",
        "Database": "Database",
        "Schemas": "Schemas",
        "Databases": "Databases",
        "ETL": "ETL",
        "Jobs": "Jobs",
        "scripts": "scripts",
        "Agile": "Agile",
        "skills": "skills",
        "root": "root",
        "cause": "cause",
        "mitigation": "mitigation",
        "plan": "plan",
        "Strong": "Strong",
        "communication": "communication",
        "relationship": "relationship",
        "collaboration": "collaboration",
        "skillsAbility": "skillsAbility",
        "pressure": "pressure",
        "environment": "environment",
        "initiative": "initiative",
        "self-motivation": "self-motivation",
        "resultsAbility": "resultsAbility",
        "technologies": "technologies",
        "POC": "POC",
        "solution": "solution",
        "problem": "problem",
        "statement": "statement",
        "Flexibility": "Flexibility",
        "member": "member",
        "matrix": "matrix",
        "diverse": "diverse",
        "project": "project",
        "Nice": "Nice",
        "familiarity": "familiarity",
        "NiFiFamiliarity": "NiFiFamiliarity",
        "BI": "BI",
        "exploration": "exploration",
        "cloud": "cloud",
        "Azure": "Azure",
        "GCPExperience": "GCPExperience",
        "machine": "machine",
        "scale": "scale",
        "phases": "phases",
        "ingestion": "ingestion",
        "feature": "feature",
        "modeling": "modeling",
        "presenting": "presenting",
        "REQUIREMENTS": "REQUIREMENTS",
        "Java/Scala/Python": "Java/Scala/Python",
        "Development": "Development",
        "framework": "framework",
        "Hive": "Hive",
        "DetailsJob": "DetailsJob",
        "Typefulltime": "Typefulltime",
        "days": "days"
      },
      "VERB": {
        "resolve": "resolve",
        "needed": "needed",
        "develop": "develop",
        "automate": "automate",
        "tasksProvide": "tasksProvide",
        "reflect": "reflect",
        "catch": "catch",
        "earlyExperiment": "earlyExperiment",
        "streamline": "streamline",
        "testing": "testing",
        "drive": "drive",
        "Help": "Help",
        "improve": "improve",
        "solve": "solve",
        "facing": "facing",
        "is": "is",
        "shadowing": "shadowing",
        "building": "building",
        "operationalizing": "operationalizing",
        "Unified": "Unified",
        "incorporate": "incorporate",
        "streaming": "streaming",
        "enhance": "enhance",
        "get": "get",
        "running": "running",
        "expand": "expand",
        "can": "can",
        "test": "test",
        "utilizing": "utilizing",
        "maintain": "maintain",
        "processing": "processing",
        "feeding": "feeding",
        "advising": "advising",
        "helping": "helping",
        "deliver": "deliver",
        "based": "based",
        "implementing": "implementing",
        "deploying": "deploying",
        "driven": "driven",
        "working": "working",
        "required": "required",
        "debugging": "debugging",
        "providing": "providing",
        "written": "written",
        "be": "be",
        "function": "function",
        "learn": "learn",
        "implement": "implement",
        "perform": "perform",
        "explore": "explore",
        "work": "work",
        "distributed": "distributed",
        "Have": "Have",
        "developing": "developing",
        "learning": "learning",
        "involving": "involving",
        "tuning": "tuning",
        "evaluating": "evaluating",
        "employeePosted": "employeePosted"
      },
      "PRT": {
        "to": "to",
        "To": "To"
      },
      "ADJ": {
        "possible": "possible",
        "new": "new",
        "cross": "cross",
        "functional": "functional",
        "full": "full",
        "best": "best",
        "other": "other",
        "relevant": "relevant",
        "technical": "technical",
        "next": "next",
        "global": "global",
        "insight": "insight",
        "Own": "Own",
        "API-based": "API-based",
        "data-driven": "data-driven",
        "reliable": "reliable",
        "internal": "internal",
        "third-party": "third-party",
        "derive": "derive",
        "complex": "complex",
        "actionable": "actionable",
        "least": "least",
        "related": "related",
        "equivalent": "equivalent",
        "multiple": "multiple",
        "end-to-end": "end-to-end",
        "teamsStrong": "teamsStrong",
        "analytical": "analytical",
        "verbal": "verbal",
        "strong": "strong",
        "organizational": "organizational",
        "high-energy": "high-energy",
        "detail-oriented": "detail-oriented",
        "proactive": "proactive",
        "able": "able",
        "independent": "independent",
        "high": "high",
        "Strong": "Strong",
        "workflow": "workflow",
        "such": "such",
        "modern": "modern",
        "integrated": "integrated"
      },
      ".": {
        "''": "''"
      },
      "NUM": {}
    }
  },
  "217750378": {
    "Company": "CyberCoders",
    "Job Title": "Remote Data Engineer - SQL, Python, R",
    "Job Details": "DescriptionIf you are a Data Engineer with experience, please read on!Top Reasons to Work with UsChance to work remotely for an up and coming start up!What You Will Be DoingIn this role, you will be interacting with partners, team members, and data to facilitate our clients' success|||| You will own the design, build, deployment, validation, and testing from inception||||  This role will require that you are able to handle and navigate conversations with different industry pros as well as understand their needs|||| This is a client-centric startup, so a positive mindset and vigorous problem-solving are required||||What You Need for this PositionAt Least 3 Years of Experience with:- SQL- R- Python- Data Analytics- Pandas- Machine Learning- Containerization- ETLPreferred Background- Project Management Experience- Client Facing i||||e|||| sales engineering, implementation, etc||||- Bachelor of Science or equivalent work experience- Contributions to open-source projects- Great communicator, Slack savvy or similarWhat's In It for You- Remote work- Medical- Dental- 401k- VisionSo, if you are a Data Engineer with experience, please apply today!Job DetailsJob Typefulltime, employeePosted 1 Day ago||||",
    "KeyWords": {
      "NOUN": {
        "Data": "Data",
        "Engineer": "Engineer",
        "experience": "experience",
        "please": "please",
        "Reasons": "Reasons",
        "UsChance": "UsChance",
        "DoingIn": "DoingIn",
        "role": "role",
        "partners": "partners",
        "team": "team",
        "members": "members",
        "data": "data",
        "clients": "clients",
        "success": "success",
        "design": "design",
        "build": "build",
        "deployment": "deployment",
        "validation": "validation",
        "inception": "inception",
        "conversations": "conversations",
        "industry": "industry",
        "pros": "pros",
        "needs": "needs",
        "startup": "startup",
        "mindset": "mindset",
        "problem-solving": "problem-solving",
        "PositionAt": "PositionAt",
        "Least": "Least",
        "Years": "Years",
        "Experience": "Experience",
        "Python-": "Python-",
        "Analytics-": "Analytics-",
        "Pandas-": "Pandas-",
        "Machine": "Machine",
        "Learning-": "Learning-",
        "Containerization-": "Containerization-",
        "ETLPreferred": "ETLPreferred",
        "Background-": "Background-",
        "Project": "Project",
        "Management": "Management",
        "Experience-": "Experience-",
        "Client": "Client",
        "Facing": "Facing",
        "i.": "i.",
        "e.": "e.",
        "sales": "sales",
        "engineering": "engineering",
        "implementation": "implementation",
        "Bachelor": "Bachelor",
        "Science": "Science",
        "work": "work",
        "Contributions": "Contributions",
        "Great": "Great",
        "communicator": "communicator",
        "Slack": "Slack",
        "savvy": "savvy",
        "Remote": "Remote",
        "Medical-": "Medical-",
        "Dental-": "Dental-",
        "VisionSo": "VisionSo",
        "today": "today",
        "Job": "Job",
        "DetailsJob": "DetailsJob",
        "Typefulltime": "Typefulltime",
        "Day": "Day"
      },
      "VERB": {
        "read": "read",
        "Work": "Work",
        "work": "work",
        "coming": "coming",
        "start": "start",
        "Will": "Will",
        "Be": "Be",
        "will": "will",
        "be": "be",
        "interacting": "interacting",
        "facilitate": "facilitate",
        "own": "own",
        "testing": "testing",
        "require": "require",
        "are": "are",
        "handle": "handle",
        "navigate": "navigate",
        "understand": "understand",
        "is": "is",
        "required": "required",
        "Need": "Need",
        "'s": "'s",
        "please": "please",
        "apply": "apply",
        "employeePosted": "employeePosted"
      },
      "ADJ": {
        "up": "up",
        "able": "able",
        "different": "different",
        "client-centric": "client-centric",
        "positive": "positive",
        "vigorous": "vigorous",
        "SQL-": "SQL-",
        "R-": "R-",
        "equivalent": "equivalent",
        "experience-": "experience-",
        "open-source": "open-source",
        "projects-": "projects-",
        "You-": "You-",
        "work-": "work-",
        "401k-": "401k-"
      },
      "PRT": {
        "to": "to",
        "up": "up"
      },
      "X": {}
    }
  },
  "217756627": {
    "Company": "Farallon Capital Management, L.L.C.",
    "Job Title": "Data Scientist",
    "Job Details": "DescriptionData Scientist: Req|||| Ph||||D||||, Ph||||D|||| ABD, or for|||| equiv||||, in Business Economics, Economics, Data Science, Finance, or rel|||| + 2 yrs exp|||| w/quantitative statistical/econometric models, data analysis packages, programming & scripting in Python, R, Stata, SQL, NoSQL & other programming/statistical languages, and software & data engineering to test investment hypotheses & develop software tools to perform such testing & provide crucial quantitative & technical analytic support|||| 5% dom|||| & int’l travel|||| Farallon Capital Management, L||||L||||C||||, San Francisco, CA|||| F/T|||| Send resume to: Farallon Capital Management, L||||L||||C||||, ATTN: FDS, One Maritime Plaza, Ste|||| 2100, San Francisco, CA 94111|||| No calls/agents/visa sponsorship||||Job DetailsJob Typefulltime, employeePosted 1 Day ago||||",
    "KeyWords": {
      "NOUN": {
        "Scientist": "Scientist",
        "Req": "Req",
        "Ph": "Ph",
        "D.": "D.",
        "ABD": "ABD",
        "equiv": "equiv",
        "Business": "Business",
        "Economics": "Economics",
        "Data": "Data",
        "Science": "Science",
        "Finance": "Finance",
        "rel": "rel",
        "yrs": "yrs",
        "exp": "exp",
        "models": "models",
        "data": "data",
        "analysis": "analysis",
        "packages": "packages",
        "Python": "Python",
        "Stata": "Stata",
        "SQL": "SQL",
        "NoSQL": "NoSQL",
        "languages": "languages",
        "software": "software",
        "engineering": "engineering",
        "investment": "investment",
        "hypotheses": "hypotheses",
        "tools": "tools",
        "support": "support",
        "dom": "dom",
        "travel": "travel",
        "Farallon": "Farallon",
        "Capital": "Capital",
        "Management": "Management",
        "L.": "L.",
        "C.": "C.",
        "San": "San",
        "Francisco": "Francisco",
        "CA": "CA",
        "F/T": "F/T",
        "Send": "Send",
        "resume": "resume",
        "ATTN": "ATTN",
        "FDS": "FDS",
        "Maritime": "Maritime",
        "Plaza": "Plaza",
        "Ste": "Ste",
        "sponsorship": "sponsorship",
        "Job": "Job",
        "DetailsJob": "DetailsJob",
        "Typefulltime": "Typefulltime",
        "Day": "Day"
      },
      "ADJ": {
        "statistical/econometric": "statistical/econometric",
        "other": "other",
        "programming/statistical": "programming/statistical",
        "such": "such",
        "crucial": "crucial",
        "quantitative": "quantitative",
        "technical": "technical",
        "analytic": "analytic",
        "int": "int",
        "calls/agents/visa": "calls/agents/visa"
      },
      "VERB": {
        "scripting": "scripting",
        "test": "test",
        "develop": "develop",
        "perform": "perform",
        "testing": "testing",
        "provide": "provide",
        "employeePosted": "employeePosted"
      },
      "PRT": {
        "to": "to"
      },
      "NUM": {
        "2100": "2100",
        "94111": "94111"
      }
    }
  },
  "217766645": {
    "Company": "Tech Domain Business IT Consulting, LLC.",
    "Job Title": "Senior Java Developer",
    "Job Details": "DescriptionTitle: Senior Java DeveloperLocations: Multiple: Herndon, VA/ Washington DC; Seattle, WA; Winston Salem, NC; San Francisco, CAExperience: 10+ Years Eligibility CriteriaCandidates must have lived in the United States for the past 5 years||||Cannot have more than 6 months cumulative outside the United States within the last 5 years||||Job Description:Under general direction, devises or modifies procedures to solve complex problems, considering computer equipment capacity and limitations, operating time and form of desired results|||| Designs, codes, tests, debugs and documents those programs|||| Competent to work at the highest technical level of all phases of applications programming activities|||| Analyzes functional business applications and design specifications for functional activities|||| Develops block diagrams and logic flow charts|||| Translates detailed design into computer software|||| Tests, debugs and refines the computer software to produce the required product|||| Prepares required documentation, including both program-level and user-level documentation|||| Enhances software to reduce operating time or improve efficiency|||| Provides technical direction to lower level programmers to ensure program deadlines are met|||| Performs all functional duties independently|||| Works on high-visibility programs, or mission critical aspects of assigned program(s)|||| Oversees the efforts of direct reporting resources and/or is responsible for the efforts of all staff assigned to a specific job||||Minimum of ten (10) years’ Java development experience, including use of the Spring frameworkStrong development experience with the following:HyperSQLGSONVB ScriptApache Codec; andWindows batch scriptingAdvanced knowledge of the Windows operating systemExperience with Java and 3rd party hardware driver integrationAbility to work directly with the customer; andDemonstrated ability to work independently or under general direction||||A degree from an accredited College/University in Software Engineering,  Computer Science, or related discipline is preferredAble to perform all functional duties independently on high-visibility programs, or mission critical aspects of a given programExperience training/mentoring less experienced personnelAble to obtain Postal clearance; andStrong communication skills||||              Job DetailsSalary$95000 - $135000 Per YearJob Typefulltime, employeePostedToday||||",
    "KeyWords": {
      "NOUN": {
        "Java": "Java",
        "DeveloperLocations": "DeveloperLocations",
        "Multiple": "Multiple",
        "Herndon": "Herndon",
        "VA/": "VA/",
        "Washington": "Washington",
        "DC": "DC",
        "Seattle": "Seattle",
        "WA": "WA",
        "Winston": "Winston",
        "Salem": "Salem",
        "NC": "NC",
        "San": "San",
        "Francisco": "Francisco",
        "CAExperience": "CAExperience",
        "Years": "Years",
        "Eligibility": "Eligibility",
        "CriteriaCandidates": "CriteriaCandidates",
        "United": "United",
        "States": "States",
        "years": "years",
        "months": "months",
        "Job": "Job",
        "Description": "Description",
        "direction": "direction",
        "procedures": "procedures",
        "problems": "problems",
        "computer": "computer",
        "equipment": "equipment",
        "capacity": "capacity",
        "limitations": "limitations",
        "operating": "operating",
        "time": "time",
        "form": "form",
        "results": "results",
        "Designs": "Designs",
        "codes": "codes",
        "tests": "tests",
        "debugs": "debugs",
        "documents": "documents",
        "programs": "programs",
        "Competent": "Competent",
        "level": "level",
        "phases": "phases",
        "applications": "applications",
        "activities": "activities",
        "Analyzes": "Analyzes",
        "business": "business",
        "design": "design",
        "specifications": "specifications",
        "Develops": "Develops",
        "block": "block",
        "diagrams": "diagrams",
        "flow": "flow",
        "charts": "charts",
        "Translates": "Translates",
        "software": "software",
        "Tests": "Tests",
        "product": "product",
        "Prepares": "Prepares",
        "documentation": "documentation",
        "Enhances": "Enhances",
        "efficiency": "efficiency",
        "Provides": "Provides",
        "programmers": "programmers",
        "program": "program",
        "deadlines": "deadlines",
        "Performs": "Performs",
        "duties": "duties",
        "high-visibility": "high-visibility",
        "mission": "mission",
        "aspects": "aspects",
        "efforts": "efforts",
        "reporting": "reporting",
        "resources": "resources",
        "staff": "staff",
        "job": "job",
        "Minimum": "Minimum",
        "ten": "ten",
        "development": "development",
        "experience": "experience",
        "use": "use",
        "Spring": "Spring",
        "following": "following",
        "HyperSQLGSONVB": "HyperSQLGSONVB",
        "ScriptApache": "ScriptApache",
        "Codec": "Codec",
        "batch": "batch",
        "knowledge": "knowledge",
        "Windows": "Windows",
        "systemExperience": "systemExperience",
        "party": "party",
        "hardware": "hardware",
        "driver": "driver",
        "integrationAbility": "integrationAbility",
        "customer": "customer",
        "ability": "ability",
        "degree": "degree",
        "College/University": "College/University",
        "Software": "Software",
        "Engineering": "Engineering",
        "Computer": "Computer",
        "Science": "Science",
        "discipline": "discipline",
        "programExperience": "programExperience",
        "clearance": "clearance",
        "communication": "communication",
        "skills": "skills",
        "DetailsSalary": "DetailsSalary",
        "Per": "Per",
        "YearJob": "YearJob",
        "Typefulltime": "Typefulltime",
        "employeePostedToday": "employeePostedToday"
      },
      "ADJ": {
        "past": "past",
        "more": "more",
        "cumulative": "cumulative",
        "last": "last",
        "general": "general",
        "complex": "complex",
        "desired": "desired",
        "highest": "highest",
        "technical": "technical",
        "functional": "functional",
        "logic": "logic",
        "detailed": "detailed",
        "required": "required",
        "program-level": "program-level",
        "user-level": "user-level",
        "lower": "lower",
        "critical": "critical",
        "assigned": "assigned",
        "direct": "direct",
        "responsible": "responsible",
        "specific": "specific",
        "frameworkStrong": "frameworkStrong",
        "accredited": "accredited",
        "related": "related",
        "preferredAble": "preferredAble",
        "less": "less",
        "experienced": "experienced",
        "personnelAble": "personnelAble",
        "Postal": "Postal",
        "andStrong": "andStrong"
      },
      "NUM": {
        "10": "10",
        "95000": "95000",
        "135000": "135000",
        "3rd": "3rd"
      },
      "VERB": {
        "have": "have",
        "lived": "lived",
        "Can": "Can",
        "devises": "devises",
        "modifies": "modifies",
        "solve": "solve",
        "considering": "considering",
        "work": "work",
        "programming": "programming",
        "refines": "refines",
        "produce": "produce",
        "required": "required",
        "including": "including",
        "reduce": "reduce",
        "improve": "improve",
        "ensure": "ensure",
        "are": "are",
        "met": "met",
        "Works": "Works",
        "Oversees": "Oversees",
        "and/or": "and/or",
        "is": "is",
        "assigned": "assigned",
        "andWindows": "andWindows",
        "scriptingAdvanced": "scriptingAdvanced",
        "operating": "operating",
        "andDemonstrated": "andDemonstrated",
        "perform": "perform",
        "given": "given",
        "training/mentoring": "training/mentoring",
        "obtain": "obtain"
      },
      "PRT": {
        "to": "to"
      }
    }
  },
  "217771211": {
    "Company": "CyberCoders",
    "Job Title": "Python Engineer",
    "Job Details": "DescriptionIf you are a Python Engineer with experience, please read on!\n+ Biotech/Pharma/Life Science experience strongly preferred + \n\nWe are a life sciences company working on providing liquid biopsies, tests that look for key molecular signatures of disease in blood, and other patient samples, without the need to take a tissue sample|||| We want to develop tests that diagnose or screen patients before they show any symptoms|||| A huge goal that other academic groups and companies are also pursuing, with large clinical trials enrolling many thousands of patients already underway|||| We do it for a fraction of the cost|||| Our main focus is early disease detection because thats what we see as the biggest need in patient care|||| If you want to be part of a trailblazing company read on||||Top Reasons to Work with Us+ We are well funded|||| Our series D back on December 19' was $55 million|||| + We are a team of industry-leading experts in our field! \n+ Be part of a 2-year-old start-up that is growing exponentially over the next few years|||| \n+ Competitive pay and full benefits packageWhat You Will Be Doing- Design, develop, and maintain performance measure visualizations and reports using data visualization tools|||| - Work with the Data Science team to understand the business needs to design an effective and dynamic visualization|||| \n- Work the Product Management team to understand and gather the user experience data||||What You Need for this Position3-5 years of experience in the following required:\n- Python, Django, AWS, SQL\n- Data Visualization tools such as Qlik Sense, Power BI, Tableau||||What's In It for YouCompetitive PayFull Benefits PackageSo, if you are a Python Engineer with experience, please apply today!\n1|||| Apply directly to this job opening here!\n\nOr\n\n2|||| E-mail directly for more information to Marcus||||Quigley@cybercoders||||comJob DetailsJob Typefulltime, employeePostedToday||||",
    "KeyWords": {
      "NOUN": {
        "Python": "Python",
        "Engineer": "Engineer",
        "experience": "experience",
        "please": "please",
        "Biotech/Pharma/Life": "Biotech/Pharma/Life",
        "Science": "Science",
        "life": "life",
        "sciences": "sciences",
        "company": "company",
        "biopsies": "biopsies",
        "tests": "tests",
        "signatures": "signatures",
        "disease": "disease",
        "blood": "blood",
        "patient": "patient",
        "samples": "samples",
        "need": "need",
        "tissue": "tissue",
        "sample": "sample",
        "patients": "patients",
        "symptoms": "symptoms",
        "goal": "goal",
        "groups": "groups",
        "companies": "companies",
        "trials": "trials",
        "thousands": "thousands",
        "fraction": "fraction",
        "cost": "cost",
        "focus": "focus",
        "detection": "detection",
        "thats": "thats",
        "care": "care",
        "part": "part",
        "Reasons": "Reasons",
        "Us+": "Us+",
        "series": "series",
        "December": "December",
        "team": "team",
        "experts": "experts",
        "field": "field",
        "Be": "Be",
        "start-up": "start-up",
        "years": "years",
        "pay": "pay",
        "benefits": "benefits",
        "Doing-": "Doing-",
        "Design": "Design",
        "develop": "develop",
        "performance": "performance",
        "measure": "measure",
        "visualizations": "visualizations",
        "reports": "reports",
        "data": "data",
        "visualization": "visualization",
        "tools": "tools",
        "Work": "Work",
        "Data": "Data",
        "business": "business",
        "Product": "Product",
        "Management": "Management",
        "user": "user",
        "following": "following",
        "Django": "Django",
        "AWS": "AWS",
        "SQL": "SQL",
        "Visualization": "Visualization",
        "Qlik": "Qlik",
        "Sense": "Sense",
        "Power": "Power",
        "BI": "BI",
        "Tableau": "Tableau",
        "YouCompetitive": "YouCompetitive",
        "PayFull": "PayFull",
        "Benefits": "Benefits",
        "PackageSo": "PackageSo",
        "today": "today",
        "job": "job",
        "E-mail": "E-mail",
        "information": "information",
        "Marcus": "Marcus",
        "Quigley": "Quigley",
        "cybercoders": "cybercoders",
        "comJob": "comJob",
        "DetailsJob": "DetailsJob",
        "Typefulltime": "Typefulltime",
        "employeePostedToday": "employeePostedToday"
      },
      "VERB": {
        "read": "read",
        "are": "are",
        "working": "working",
        "providing": "providing",
        "look": "look",
        "take": "take",
        "want": "want",
        "develop": "develop",
        "diagnose": "diagnose",
        "show": "show",
        "pursuing": "pursuing",
        "enrolling": "enrolling",
        "do": "do",
        "is": "is",
        "see": "see",
        "be": "be",
        "Work": "Work",
        "funded": "funded",
        "was": "was",
        "growing": "growing",
        "Will": "Will",
        "Be": "Be",
        "maintain": "maintain",
        "using": "using",
        "understand": "understand",
        "needs": "needs",
        "design": "design",
        "gather": "gather",
        "Need": "Need",
        "required": "required",
        "'s": "'s",
        "please": "please",
        "apply": "apply",
        "Apply": "Apply",
        "opening": "opening"
      },
      "ADJ": {
        "liquid": "liquid",
        "key": "key",
        "molecular": "molecular",
        "other": "other",
        "screen": "screen",
        "huge": "huge",
        "academic": "academic",
        "large": "large",
        "clinical": "clinical",
        "many": "many",
        "main": "main",
        "early": "early",
        "biggest": "biggest",
        "patient": "patient",
        "trailblazing": "trailblazing",
        "Top": "Top",
        "industry-leading": "industry-leading",
        "2-year-old": "2-year-old",
        "next": "next",
        "few": "few",
        "Competitive": "Competitive",
        "full": "full",
        "effective": "effective",
        "dynamic": "dynamic",
        "Position3-5": "Position3-5",
        "such": "such",
        "more": "more"
      },
      "PRT": {
        "to": "to"
      },
      "NUM": {
        "55": "55",
        "million": "million"
      }
    }
  },
  "217771854": {
    "Company": "CyberCoders",
    "Job Title": "Sr. Backend Engineer - Python & AWS/Azure/GCP - 100% REMOTE!",
    "Job Details": "DescriptionIf you are a Sr|||| Back-end Engineer with experience in Python, as well as either AWS/Azure/GCP, please read on!\nLocated in Redwood City, we specialize in providing our clients with a secure platform to surf the web with privacy|||| We ensure that our clients feel safe and comforted to be successful and feel that their web security is endless||||  We have been in business for over 10 years and are growing a ton!\n\nWe are looking for a strong Back-End Engineer who is going to be excellent in Python, as well as either AWS/Azure/GCP|||| Any experience working on the front-end is a PLUS!  You will be working with the Enterprise team, responsible for enhancing our product and collaborating with the team to create code|||| You will also be deploying, and troubleshooting our application in addition to building large scale systems- CI/CD, DevOps|||| etc||||\n\n*This position is 100% REMOTE*What You Will Be Doing-Using back-end technologies to create code-Working collaboratively in a team\n-Enhancing our product and applicationWhat You Need for this PositionAt Least 3 Years of experience and knowledge of:\n- Python\n- AWS\n- Networking Concepts\n- C++\n- JavaScript\n- CloudSo, if you are a Sr|||| Back-end Engineer with experience in Python, as well as either AWS/Azure/GCP, please apply today!Job DetailsJob Typefulltime, employeePostedToday||||",
    "KeyWords": {
      "NOUN": {
        "Sr.": "Sr.",
        "Back-end": "Back-end",
        "Engineer": "Engineer",
        "experience": "experience",
        "Python": "Python",
        "AWS/Azure/GCP": "AWS/Azure/GCP",
        "please": "please",
        "Redwood": "Redwood",
        "City": "City",
        "clients": "clients",
        "secure": "secure",
        "platform": "platform",
        "web": "web",
        "privacy": "privacy",
        "security": "security",
        "business": "business",
        "years": "years",
        "ton": "ton",
        "Back-End": "Back-End",
        "front-end": "front-end",
        "Enterprise": "Enterprise",
        "team": "team",
        "product": "product",
        "code": "code",
        "application": "application",
        "addition": "addition",
        "CI/CD": "CI/CD",
        "DevOps": "DevOps",
        "etc": "etc",
        "position": "position",
        "REMOTE": "REMOTE",
        "technologies": "technologies",
        "PositionAt": "PositionAt",
        "Least": "Least",
        "Years": "Years",
        "knowledge": "knowledge",
        "AWS": "AWS",
        "Networking": "Networking",
        "Concepts": "Concepts",
        "C++": "C++",
        "JavaScript": "JavaScript",
        "CloudSo": "CloudSo",
        "today": "today",
        "Job": "Job",
        "DetailsJob": "DetailsJob",
        "Typefulltime": "Typefulltime",
        "employeePostedToday": "employeePostedToday"
      },
      "VERB": {
        "read": "read",
        "Located": "Located",
        "specialize": "specialize",
        "providing": "providing",
        "surf": "surf",
        "ensure": "ensure",
        "feel": "feel",
        "comforted": "comforted",
        "be": "be",
        "is": "is",
        "have": "have",
        "been": "been",
        "are": "are",
        "growing": "growing",
        "looking": "looking",
        "going": "going",
        "working": "working",
        "will": "will",
        "enhancing": "enhancing",
        "collaborating": "collaborating",
        "create": "create",
        "deploying": "deploying",
        "troubleshooting": "troubleshooting",
        "building": "building",
        "Will": "Will",
        "Be": "Be",
        "-Enhancing": "-Enhancing",
        "Need": "Need",
        "please": "please",
        "apply": "apply"
      },
      "PRT": {
        "to": "to"
      },
      "ADJ": {
        "successful": "successful",
        "web": "web",
        "endless": "endless",
        "strong": "strong",
        "excellent": "excellent",
        "PLUS": "PLUS",
        "responsible": "responsible",
        "large": "large",
        "scale": "scale",
        "systems-": "systems-",
        "Doing-Using": "Doing-Using",
        "back-end": "back-end",
        "code-Working": "code-Working"
      },
      "NUM": {
        "100": "100"
      }
    }
  },
  "217772196": {
    "Company": "CyberCoders",
    "Job Title": "Sr. Genomics Data Engineer  - Spark, Python, AI",
    "Job Details": "DescriptionIf you are a Sr|||| Data Engineer with a background in Human Genomics and strong Apache Spark experience, please read on!\nHeadquartered out of beautiful Oakland, we are a cutting-edge AI-Driven Genomics Biotech company! Established in 2011, we analyze and interpret complex genomic data from raw data to variant cells, from whole genome, exome, or panel tests to increase diagnostic yield|||| We are trailblazers, tenaciously deciphering human biology when it comes to hereditary disease and oncology|||| Our platform substantially reduces genome interpretation time in the diagnosis of monogenic diseases, which allows cost-effective, automated reanalysis of undiagnosed cases||||\n\nIf you have a passion for the complex and beautiful combination of Data and Genomics with a strong background in Apache Spark, we would love to hear from you!Top Reasons to Work with Us1|||| Fast-Growing AI-Driven Genomics Company!2|||| Opportunity for Professional Growth!\n3|||| Competitive Base Salary, Benefits, and Great Company Culture!What You Will Be Doing- Build out a big data distributed architecture capable of efficiently processing large-scale genomics data||||- Develop / deploy bioinformatics and AI analysis algorithms at scale||||\n- Build automated production-quality data processing systems||||\n- Interact and collaborate with scientists to clearly define / iterate on requirements||||\n- Keep abreast of new software data engineering and data science technologies||||\n- Aggregate / analyze genomic and other types of clinical data to find novel insights||||\n- Develop code to implement analysis workflows in a robust and reproducible fashion||||\n- Follow processes to improve transparency and reliability of applications, reducing project risks for on-time milestones||||\n- Educate other scientists, engineers, and management on the methods developed and how they apply to the subject domain and customer needs||||What You Need for this Position- Bachelor's Degree in Computer Science, Technology, or related|||| - 2+ years of experience working with Genomics Data||||\n- Must have experience with cluster-computing framework Apache Spark|||| \n- Programming/scripting experience with Python||||\n\nBonus Points:\n- Background using Scala||||\n- Proficiency with SQL database and scripting||||\n- Experience with Amazon Web Services (AWS)||||What's In It for YouFor your hard work and dedication, you will be rewarded with a competitive base salary, and excellent benefits including but not limited to:- Salary ($150k - $180k DOE)\n- Vacation/PTO \n- Medical\n- Dental\n- Vision\n- Bonus (10%)\n- 401k\n- EquitySo, if you are a Sr|||| Genomics Data Engineer with Apache Spark experience, please apply today!Job DetailsSalary$150000 - $200000 Per YearJob Typefulltime, employeePosted 5 days ago||||",
    "KeyWords": {
      "NOUN": {
        "Sr.": "Sr.",
        "Data": "Data",
        "Engineer": "Engineer",
        "background": "background",
        "Human": "Human",
        "Genomics": "Genomics",
        "Apache": "Apache",
        "Spark": "Spark",
        "experience": "experience",
        "please": "please",
        "Oakland": "Oakland",
        "Biotech": "Biotech",
        "company": "company",
        "data": "data",
        "cells": "cells",
        "genome": "genome",
        "exome": "exome",
        "panel": "panel",
        "tests": "tests",
        "yield": "yield",
        "trailblazers": "trailblazers",
        "biology": "biology",
        "disease": "disease",
        "oncology": "oncology",
        "platform": "platform",
        "interpretation": "interpretation",
        "time": "time",
        "diagnosis": "diagnosis",
        "diseases": "diseases",
        "cost-effective": "cost-effective",
        "reanalysis": "reanalysis",
        "cases": "cases",
        "passion": "passion",
        "combination": "combination",
        "Reasons": "Reasons",
        "Us1": "Us1",
        "Company": "Company",
        "Opportunity": "Opportunity",
        "Professional": "Professional",
        "Growth": "Growth",
        "Base": "Base",
        "Salary": "Salary",
        "Benefits": "Benefits",
        "Great": "Great",
        "Culture": "Culture",
        "Doing-": "Doing-",
        "Build": "Build",
        "architecture": "architecture",
        "genomics": "genomics",
        "Develop": "Develop",
        "deploy": "deploy",
        "bioinformatics": "bioinformatics",
        "AI": "AI",
        "analysis": "analysis",
        "algorithms": "algorithms",
        "scale": "scale",
        "production-quality": "production-quality",
        "systems": "systems",
        "Interact": "Interact",
        "collaborate": "collaborate",
        "scientists": "scientists",
        "iterate": "iterate",
        "requirements": "requirements",
        "Keep": "Keep",
        "abreast": "abreast",
        "software": "software",
        "engineering": "engineering",
        "science": "science",
        "technologies": "technologies",
        "Aggregate": "Aggregate",
        "types": "types",
        "insights": "insights",
        "code": "code",
        "workflows": "workflows",
        "fashion": "fashion",
        "processes": "processes",
        "transparency": "transparency",
        "reliability": "reliability",
        "applications": "applications",
        "project": "project",
        "risks": "risks",
        "milestones": "milestones",
        "Educate": "Educate",
        "engineers": "engineers",
        "management": "management",
        "methods": "methods",
        "subject": "subject",
        "domain": "domain",
        "customer": "customer",
        "needs": "needs",
        "Position-": "Position-",
        "Bachelor": "Bachelor",
        "Degree": "Degree",
        "Computer": "Computer",
        "Science": "Science",
        "Technology": "Technology",
        "years": "years",
        "Must": "Must",
        "framework": "framework",
        "Python": "Python",
        "Bonus": "Bonus",
        "Points": "Points",
        "Scala": "Scala",
        "Proficiency": "Proficiency",
        "SQL": "SQL",
        "database": "database",
        "scripting": "scripting",
        "Experience": "Experience",
        "Amazon": "Amazon",
        "Web": "Web",
        "Services": "Services",
        "AWS": "AWS",
        "YouFor": "YouFor",
        "work": "work",
        "dedication": "dedication",
        "base": "base",
        "salary": "salary",
        "benefits": "benefits",
        "DOE": "DOE",
        "Vision": "Vision",
        "EquitySo": "EquitySo",
        "today": "today",
        "Job": "Job",
        "DetailsSalary": "DetailsSalary",
        "Per": "Per",
        "YearJob": "YearJob",
        "Typefulltime": "Typefulltime",
        "days": "days"
      },
      "VERB": {
        "read": "read",
        "Headquartered": "Headquartered",
        "are": "are",
        "Established": "Established",
        "analyze": "analyze",
        "interpret": "interpret",
        "variant": "variant",
        "increase": "increase",
        "deciphering": "deciphering",
        "comes": "comes",
        "reduces": "reduces",
        "allows": "allows",
        "automated": "automated",
        "have": "have",
        "would": "would",
        "love": "love",
        "hear": "hear",
        "Work": "Work",
        "Will": "Will",
        "Be": "Be",
        "distributed": "distributed",
        "processing": "processing",
        "define": "define",
        "find": "find",
        "Develop": "Develop",
        "implement": "implement",
        "improve": "improve",
        "reducing": "reducing",
        "developed": "developed",
        "apply": "apply",
        "Need": "Need",
        "related": "related",
        "working": "working",
        "Programming/scripting": "Programming/scripting",
        "using": "using",
        "'s": "'s",
        "will": "will",
        "be": "be",
        "rewarded": "rewarded",
        "including": "including",
        "please": "please",
        "employeePosted": "employeePosted"
      },
      "ADJ": {
        "beautiful": "beautiful",
        "cutting-edge": "cutting-edge",
        "AI-Driven": "AI-Driven",
        "complex": "complex",
        "genomic": "genomic",
        "raw": "raw",
        "whole": "whole",
        "diagnostic": "diagnostic",
        "human": "human",
        "hereditary": "hereditary",
        "genome": "genome",
        "monogenic": "monogenic",
        "undiagnosed": "undiagnosed",
        "strong": "strong",
        "Top": "Top",
        "Fast-Growing": "Fast-Growing",
        "Competitive": "Competitive",
        "big": "big",
        "capable": "capable",
        "large-scale": "large-scale",
        "new": "new",
        "other": "other",
        "clinical": "clinical",
        "novel": "novel",
        "robust": "robust",
        "reproducible": "reproducible",
        "Follow": "Follow",
        "on-time": "on-time",
        "cluster-computing": "cluster-computing",
        "hard": "hard",
        "competitive": "competitive",
        "excellent": "excellent",
        "limited": "limited",
        "Medical": "Medical",
        "Dental": "Dental"
      },
      "NUM": {
        "10": "10",
        "150000": "150000",
        "200000": "200000",
        "2+": "2+",
        "150k": "150k",
        "180k": "180k",
        "401k": "401k"
      },
      "PRT": {
        "to": "to",
        "out": "out",
        "'s": "'s"
      },
      "X": {}
    }
  },
  "7fb56dd9-b7a9-4dba-8615-7cc813f63376": {
    "Company": "Atrium Staffing",
    "Job Title": "Test Engineer, Hardware",
    "Job Details": "DescriptionThis company is an industry leader in their niche within the consumer products industry|||| Their research and application combines biological innovation with technical engineering and development|||| The company is forward thinking, fast-paced and they execute with a lean team of industry professionals||||  They are currently looking to hire a Test Engineer, Hardware||||\nSalary/Hourly Rate:\nBased on experience\nPosition Description:\nThe Test Engineer, Hardware will define test methodology to improve the user experience and be responsible for product validation|||| This is a lab based position ideal for a Test Engineer who likes working on Hardware doing soldering and testing|||| The Engineer will work with senior engineers in the Hardware team and collaborate cross functionally||||\nResponsibilities of the Test Engineer, Hardware:\n\n Prepare and execute test plans for hardware on an electronic, handled consumer product\n Validate consumer hardware products\n Testing using oscilloscopes, micrometers, power analyzers, Vans, etc \n Soldering of circuit boards\n Set timelines and oversee projects on a day to day basis\n Assist senior engineers with assignments as needed\n Use Python\n Set test methodologies for new and updated interfaces\n Work cross functionally with internal teams and external manufactures\n Diagnose and debug hardware and firmware issues\n\n Qualifications for the Test Engineer, Hardware:\n\n Soldering and lab experience in regards to hardware validation work is required\n Python experience highly desired\n 2-5 years experience in lab validation in areas including RF validation, Power supply, custom analog amplifier circuits, input device validation, sensors- in academic or industry settings\n Experience with real-time scopes, sampling scopes, TDR/TDT, VNA/ENA, spectrum analyzer, impedance analyzer, amp-probes, logic analyzers, protocol analyzers\n Professional communication skills – oral and written\n Experience with modern analog, digital electronic circuits or transmission line theory a plus\n\n Education Requirements:\n\n Bachelor’s Degree in Electrical Engineer or related preferred\n\nBenefits:\n\nEligible for Atrium Care Package\n\nThe post Test Engineer, Hardware appeared first on Atrium||||Job DetailsPosted 4 days ago||||",
    "KeyWords": {
      "NOUN": {
        "company": "company",
        "industry": "industry",
        "leader": "leader",
        "niche": "niche",
        "consumer": "consumer",
        "products": "products",
        "research": "research",
        "application": "application",
        "combines": "combines",
        "innovation": "innovation",
        "engineering": "engineering",
        "development": "development",
        "team": "team",
        "professionals": "professionals",
        "Test": "Test",
        "Engineer": "Engineer",
        "Hardware": "Hardware",
        "Rate": "Rate",
        "experience": "experience",
        "Position": "Position",
        "Description": "Description",
        "test": "test",
        "methodology": "methodology",
        "user": "user",
        "product": "product",
        "validation": "validation",
        "lab": "lab",
        "position": "position",
        "ideal": "ideal",
        "soldering": "soldering",
        "testing": "testing",
        "engineers": "engineers",
        "collaborate": "collaborate",
        "cross": "cross",
        "Responsibilities": "Responsibilities",
        "Prepare": "Prepare",
        "plans": "plans",
        "hardware": "hardware",
        "Validate": "Validate",
        "oscilloscopes": "oscilloscopes",
        "micrometers": "micrometers",
        "power": "power",
        "analyzers": "analyzers",
        "Vans": "Vans",
        "Soldering": "Soldering",
        "circuit": "circuit",
        "boards": "boards",
        "Set": "Set",
        "timelines": "timelines",
        "projects": "projects",
        "day": "day",
        "basis": "basis",
        "Assist": "Assist",
        "assignments": "assignments",
        "Use": "Use",
        "Python": "Python",
        "methodologies": "methodologies",
        "interfaces": "interfaces",
        "Work": "Work",
        "teams": "teams",
        "manufactures": "manufactures",
        "Diagnose": "Diagnose",
        "debug": "debug",
        "firmware": "firmware",
        "issues": "issues",
        "Qualifications": "Qualifications",
        "regards": "regards",
        "work": "work",
        "years": "years",
        "areas": "areas",
        "RF": "RF",
        "Power": "Power",
        "supply": "supply",
        "custom": "custom",
        "analog": "analog",
        "circuits": "circuits",
        "input": "input",
        "device": "device",
        "sensors-": "sensors-",
        "settings": "settings",
        "Experience": "Experience",
        "scopes": "scopes",
        "TDR/TDT": "TDR/TDT",
        "VNA/ENA": "VNA/ENA",
        "spectrum": "spectrum",
        "analyzer": "analyzer",
        "impedance": "impedance",
        "protocol": "protocol",
        "Professional": "Professional",
        "communication": "communication",
        "skills": "skills",
        "transmission": "transmission",
        "line": "line",
        "theory": "theory",
        "Education": "Education",
        "Requirements": "Requirements",
        "Bachelor": "Bachelor",
        "Degree": "Degree",
        "Electrical": "Electrical",
        "Benefits": "Benefits",
        "Atrium": "Atrium",
        "Care": "Care",
        "Package": "Package",
        "post": "post",
        "Job": "Job",
        "days": "days"
      },
      "VERB": {
        "is": "is",
        "thinking": "thinking",
        "execute": "execute",
        "are": "are",
        "looking": "looking",
        "hire": "hire",
        "Based": "Based",
        "will": "will",
        "define": "define",
        "improve": "improve",
        "be": "be",
        "based": "based",
        "likes": "likes",
        "working": "working",
        "doing": "doing",
        "work": "work",
        "Testing": "Testing",
        "using": "using",
        "needed": "needed",
        "hardware": "hardware",
        "required": "required",
        "desired": "desired",
        "including": "including",
        "sampling": "sampling",
        "written": "written",
        "related": "related",
        "appeared": "appeared",
        "DetailsPosted": "DetailsPosted"
      },
      "ADJ": {
        "technical": "technical",
        "fast-paced": "fast-paced",
        "lean": "lean",
        "Salary/Hourly": "Salary/Hourly",
        "responsible": "responsible",
        "senior": "senior",
        "electronic": "electronic",
        "handled": "handled",
        "oversee": "oversee",
        "new": "new",
        "updated": "updated",
        "internal": "internal",
        "external": "external",
        "lab": "lab",
        "academic": "academic",
        "real-time": "real-time",
        "amp-probes": "amp-probes",
        "logic": "logic",
        "oral": "oral",
        "modern": "modern",
        "digital": "digital",
        "preferred": "preferred",
        "Eligible": "Eligible"
      },
      "PRT": {
        "to": "to"
      },
      "X": {},
      "NUM": {}
    }
  }
}
